Workbook

Sheet Pattern
A1: Cat. | B1: Categoria | C1: Resoconto (cosa dicono i dati) | D1: Fatti a supporto | E1: Solidità dell'evidenza | F1: Limiti: cosa NON possiamo dedurre | G1: Spunti per il design (ipotesi da verificare) | H1: N. fatti
A2: C1 | B2: Abitudini online e contatti con sconosciuti | C2: Scrivono soprattutto su WhatsApp, Instagram e TikTok. La maggior parte ha il profilo privato, spesso per scelta propria. I messaggi da sconosciuti sono frequenti, ma le studentesse intervistate dicono di scrivere quasi solo con persone che conoscono. | D2: Q02, Q03, Q04, Q05, S01–S04, S06, S07 | E2: Alta (questionario + intervista) | F2: Questionario quasi tutto maschile; per le chat dei videogiochi e Discord non ci sono dati qualitativi. | G2: Quali canali coprire per primi (WhatsApp, Instagram, TikTok)? Le chat dei videogiochi meritano un approfondimento? | H2: =COUNTIF(Fatti!$G:$G,A2) -> #NAME?
A3: C2 | B3: Come valutano se un profilo è affidabile | C3: Il criterio principale è sociale: amici in comune, chi lo segue, "lo conoscono le mie amiche". Poi vengono segnali superficiali (numero di follower, foto profilo, aspetto) usati in modo incoerente: per alcuni pochi follower sono un segnale di falso, per altri anche 600 lo sono. Qualcuno usa strategie più evolute (età dell'account, ricerca dell'immagine, prefisso estero). | D3: Q06, Q07, Q22, S05, S08–S14 | E3: Alta (questionario + intervista + esercizio) | F3: La codifica della domanda aperta è per parole chiave: va controllata a mano (foglio "Q aperta codificata"). Un solo esercizio con due profili. | G3: Ipotesi: insegnare che gli "amici in comune" e i follower non bastano come garanzia; allenare a segnali più affidabili (età dell'account, ricerca inversa dell'immagine, comportamento in chat). | H3: =COUNTIF(Fatti!$G:$G,A3) -> #NAME?
A4: C3 | B4: Fiducia nelle proprie capacità vs comportamenti reali | C4: Circa 3 su 4 si sentono capaci di accorgersi di un profilo falso e di una foto fatta con l'IA. Ma quando hanno un dubbio su un contenuto, la metà non fa niente e l'azione più comune è guardare i commenti; chiedere a qualcuno è rarissimo. La passività riguarda tutti: chi ha poca fiducia è anzi ancora più passivo (14 su 21), quindi non si può dire che sia la sicurezza a rendere passivi. Due segnali di sovrastima: 14 dei 21 che non sanno cos'è un deepfake si danno 4-5 nel riconoscere foto IA, e più della metà di chi si sente capace di riconoscerle non saprebbe bene come agire se toccasse a loro. | D4: Q08–Q14, S15 | E4: Media: sono autovalutazioni, nell'intervista c'è un solo esercizio | F4: Un'autovalutazione alta non è una competenza misurata. Dai dati non si può dire che "non sanno riconoscere" i falsi: si può dire che la fiducia dichiarata non corrisponde ad azioni di verifica. | G4: Da verificare con un test pratico (es. riconoscere N foto vere/IA) per misurare la competenza reale. | H4: =COUNTIF(Fatti!$G:$G,A4) -> #NAME?
A5: C4 | B5: Deepfake e contenuti falsi tra coetanei | C5: I contenuti modificati con l'IA girano tra coetanei (quasi 4 su 5 li hanno visti). Pochissimi li considerano una cosa seria: in genere "dipende" da quanto è pesante o sono uno scherzo. La gravità si giudica dalla reazione visibile della vittima ("se ride è uno scherzo"). Una studentessa racconta una chat creata contro di lei con le sue foto; la sua paura principale era che venissero modificate con l'IA. | D5: Q15, Q16, S16, S17, S19, S30, S33 | E5: Alta (questionario + intervista) | F5: Il questionario chiede cosa pensano "gli altri ragazzi", non il rispondente. Il caso di Aurora è una singola esperienza. | G5: Ipotesi: lavorare sulla percezione del danno ("ridere non vuol dire stare bene") e sul ruolo di chi assiste. | H5: =COUNTIF(Fatti!$G:$G,A5) -> #NAME?
A6: C5 | B6: Riconoscere l'adescamento e le richieste di foto | C6: Davanti alla stessa chat di adescamento, le ragazze non concordano su quando scatta il campanello d'allarme: per alcune la confidenza eccessiva troppo presto, per altre la segretezza ("non dirlo ai tuoi") o la richiesta di una foto. Il rifiuto di mandare foto sessuali è netto, ma su una foto "normale" la soglia dipende dal tempo e dal sentirsi in confidenza. Le richieste di foto raccontate venivano da persone conosciute, non da sconosciuti. | D6: S20–S24, S08 | E6: Bassa-media: 5 ragazze di 13-14 anni, in gruppo | F6: Non generalizzabile al target, né ai ragazzi maschi. In gruppo le risposte si influenzano a vicenda. | G6: Ipotesi: un training che mostri l'escalation tipica (lusinga → segretezza → cambio di piattaforma → richiesta). Approfondire nelle prossime interviste i casi con persone "semi-conosciute". | H6: =COUNTIF(Fatti!$G:$G,A6) -> #NAME?
A7: C6 | B7: Chiedere aiuto: a chi, e perché no | C7: Il primo confidente è un amico o un'amica; quasi 1 su 5 non ne parlerebbe con nessuno (nessuna delle 10 ragazze del questionario). Genitori e docenti sono scelti raramente come primo riferimento. Le ragazze esprimono riluttanza a coinvolgere i genitori (preferiscono "piuttosto i carabinieri") e temono che il prof veda la chat. Il docente attribuisce questa riluttanza a vergogna e paura di punizioni. Pochi sanno come agire se circolasse un'immagine falsa di sé. Per informarsi userebbero soprattutto Google, adulti, amici e IA; per confidarsi vogliono "una persona vera". | D7: Q17–Q20, S18, S25–S28, S31, D06–D08, D14–D17 | E7: Alta (tre fonti concordano) | F7: La risposta corale "prima con i genitori" (S27) è arrivata dopo una domanda diretta dell'intervistatore: va pesata meno. Le ragioni del docente (D15) sono sue opinioni. | G7: Ipotesi: gli amici sono il canale principale, quindi conviene preparare anche chi riceve la confidenza ("come aiutare un'amica"). Percorsi di aiuto chiari e graduali, che non obblighino a coinvolgere subito i genitori. | H7: =COUNTIF(Fatti!$G:$G,A7) -> #NAME?
A8: C7 | B8: Prevenzione e ruolo della scuola | C8: Quasi nessuno ricorda attività di prevenzione; chi le cita parla di conferenze sul cyberbullismo o di educazione civica. A scuola la regolamentazione sull'IA è appena iniziata, mancano spazi di confronto tra studenti e il telefono è vietato. Nell'unico caso concreto raccontato, la scuola non è intervenuta in modo percepito come adeguato. Alcuni rispondenti chiedono più informazione. | D8: Q21, Q23, D01–D05, D07, D10, D12, D13, S32 | E8: Media | F8: Un solo docente e una sola scuola per le informazioni sull'istituto. "Non ricordo attività" non significa che non ce ne siano state. | G8: Con il divieto del telefono a scuola, lo strumento va pensato per l'uso fuori dall'orario scolastico (o con dispositivi della scuola). | H8: =COUNTIF(Fatti!$G:$G,A8) -> #NAME?
A9: C8 | B9: Idea di progetto: forum anonimo e supporto | C9: Il forum riceve un interesse condizionato: sì se è anonimo (le ragazze citano NGL) e se si è sicuri che gli altri siano chi dicono. Un'intervistata dubita che molti racconterebbero la propria esperienza. Il docente lo ritiene utile per sentirsi meno soli, ma chiede supervisione discreta, protezione dagli screenshot e un accesso facile all'aiuto (esperti, numeri utili). Nel questionario solo il 4% cercherebbe informazioni in un forum. | D9: S29, S28, D09, D19–D23, Q20 | E9: Media-bassa | F9: L'idea del forum è stata proposta dagli intervistatori: c'è il rischio di risposte compiacenti. Il dato del questionario (4%) riguarda la ricerca di informazioni, non la condivisione. | G9: Tensione da risolvere: anonimato vs autenticità vs supervisione. Da verificare se i ragazzi leggerebbero esperienze altrui anche senza scriverne. | H9: =COUNTIF(Fatti!$G:$G,A9) -> #NAME?
A10: C9 | B10: Come comunicare con i ragazzi | C10: Il docente consiglia un tono alla pari, un linguaggio semplice e diretto e nessuna imposizione: ciò che sembra imposto viene rifiutato. Racconta che una domanda amichevole è bastata a far aprire uno studente. | D10: D11, D18 | E10: Bassa: una sola fonte | F10: È l'esperienza di un singolo docente. | G10: Da verificare con i ragazzi (es. confronto tra testi con toni diversi). | H10: =COUNTIF(Fatti!$G:$G,A10) -> #NAME?

Sheet Fatti
A1: Tabella dei fatti – una riga per ogni elemento rilevato (dati, non interpretazioni)
A2: S = intervista di gruppo alle studentesse (07/10) · D = intervista al docente (09/10) · Q = questionario online. Nomi delle studentesse di fantasia. La colonna Categoria rimanda al foglio "Pattern".
A4: ID | B4: Fonte | C4: Chi | D4: Tema / domanda | E4: Fatto osservato | F4: Riferimento audio | G4: Categoria | H4: Nome categoria | I4: NOTE
A5: S01 | B5: Intervista studentesse 07/10 | C5: Giulia, Sofia, Martina | D5: Abitudini online | E5: Scrivono soprattutto (Giulia) o solo (Sofia, Martina) con persone che conoscono. | G5: C1 | H5: =IFERROR(INDEX(Pattern!$B:$B,MATCH(G5,Pattern!$A:$A,0)),"") -> Abitudini online e contatti con sconosciuti
A6: S02 | B6: Intervista studentesse 07/10 | C6: Aurora | D6: Abitudini online | E6: Le è capitato di interagire anche con persone che non conosce. | G6: C1 | H6: =IFERROR(INDEX(Pattern!$B:$B,MATCH(G6,Pattern!$A:$A,0)),"") -> Abitudini online e contatti con sconosciuti
A7: S03 | B7: Intervista studentesse 07/10 | C7: Tutte (5) | D7: Profili social | E7: Tutte hanno il profilo privato. | G7: C1 | H7: =IFERROR(INDEX(Pattern!$B:$B,MATCH(G7,Pattern!$A:$A,0)),"") -> Abitudini online e contatti con sconosciuti
A8: S04 | B8: Intervista studentesse 07/10 | C8: Tutte (5) | D8: Profili social | E8: Giulia l'ha reso privato su consiglio della madre; Aurora, Martina e Chiara da sole "per precauzione"; Sofia "perché non voglio che altre persone lo vedano". | G8: C1 | H8: =IFERROR(INDEX(Pattern!$B:$B,MATCH(G8,Pattern!$A:$A,0)),"") -> Abitudini online e contatti con sconosciuti
A9: S05 | B9: Intervista studentesse 07/10 | C9: Giulia | D9: Contatti con sconosciuti | E9: Ha un'amica conosciuta online, ma non ha avuto diffidenza "perché già la conoscevo tramite un po' di amiche". Nessun contatto con persone del tutto sconosciute. | G9: C2 | H9: =IFERROR(INDEX(Pattern!$B:$B,MATCH(G9,Pattern!$A:$A,0)),"") -> Come valutano se un profilo è affidabile
A10: S06 | B10: Intervista studentesse 07/10 | C10: Sofia, Martina | D10: Contatti con sconosciuti | E10: Una volta contattate da uno sconosciuto: bloccato subito ("non mi fidavo" / "non lo conosceva nessuno"). | G10: C1 | H10: =IFERROR(INDEX(Pattern!$B:$B,MATCH(G10,Pattern!$A:$A,0)),"") -> Abitudini online e contatti con sconosciuti
A11: S07 | B11: Intervista studentesse 07/10 | C11: Chiara | D11: Contatti con sconosciuti | E11: "Io mai nessuno online." | G11: C1 | H11: =IFERROR(INDEX(Pattern!$B:$B,MATCH(G11,Pattern!$A:$A,0)),"") -> Abitudini online e contatti con sconosciuti
A12: S08 | B12: Intervista studentesse 07/10 | C12: Aurora | D12: Contatti con sconosciuti | E12: Ha accettato un ragazzo sconosciuto perché le amiche lo seguivano; "sembrava più grande"; dovevano uscire, poi ha perso interesse perché non sapeva bene "com'era fatto". | F12: Estratto 1 (02:50) | G12: C2 | H12: =IFERROR(INDEX(Pattern!$B:$B,MATCH(G12,Pattern!$A:$A,0)),"") -> Come valutano se un profilo è affidabile
A13: S09 | B13: Intervista studentesse 07/10 | C13: Giulia | D13: Segnali di affidabilità | E13: Primo segnale di dubbio: se è "aggressivo, violento". Con amici in comune "mi fa pensare che è a posto"; senza, diventa più diffidente. | G13: C2 | H13: =IFERROR(INDEX(Pattern!$B:$B,MATCH(G13,Pattern!$A:$A,0)),"") -> Come valutano se un profilo è affidabile
A14: S10 | B14: Intervista studentesse 07/10 | C14: Sofia | D14: Segnali di affidabilità | E14: Si insospettisce "se inizia a fare domande un po' scomode". | G14: C2 | H14: =IFERROR(INDEX(Pattern!$B:$B,MATCH(G14,Pattern!$A:$A,0)),"") -> Come valutano se un profilo è affidabile
A15: S11 | B15: Intervista studentesse 07/10 | C15: Aurora | D15: Segnali di affidabilità | E15: Guarda la foto profilo; evita chi pubblica storie con pistole (pur conoscendo "brave persone" che lo fanno); evita chi chiede dove abita. | G15: C2 | H15: =IFERROR(INDEX(Pattern!$B:$B,MATCH(G15,Pattern!$A:$A,0)),"") -> Come valutano se un profilo è affidabile
A16: S12 | B16: Intervista studentesse 07/10 | C16: Chiara | D16: Segnali di affidabilità | E16: Su WhatsApp guarda la provenienza del numero e blocca i numeri esteri; su Instagram prima segue lei lo sconosciuto e poi, se va bene, lo accetta. | G16: C2 | H16: =IFERROR(INDEX(Pattern!$B:$B,MATCH(G16,Pattern!$A:$A,0)),"") -> Come valutano se un profilo è affidabile
A17: S13 | B17: Intervista studentesse 07/10 | C17: Sofia, Aurora, Giulia | D17: Esercizio 1 – due profili | E17: Giudicano i profili da aspetto e "normalità" delle foto ("sembra fake tantissimo", "questo è più bello", "sembra più una persona vera"); notano il tag dell'università. Sofia: "l'apparenza può ingannare". | G17: C2 | H17: =IFERROR(INDEX(Pattern!$B:$B,MATCH(G17,Pattern!$A:$A,0)),"") -> Come valutano se un profilo è affidabile
A18: S14 | B18: Intervista studentesse 07/10 | C18: Aurora, Giulia, Chiara | D18: Esercizio 1 – due profili | E18: Usano i follower come indizio ma in modo incoerente: 436 follower "non so"; per Aurora 600 follower "già mi sembra una cosa finta". Confrontano con il proprio numero di follower. | G18: C2 | H18: =IFERROR(INDEX(Pattern!$B:$B,MATCH(G18,Pattern!$A:$A,0)),"") -> Come valutano se un profilo è affidabile | I18: questo può essere un esempio di indicatore errato/incoerente da usare.
A19: S15 | B19: Intervista studentesse 07/10 | C19: Giulia, Aurora | D19: Esercizio 2 – foto IA | E19: Il gruppo individua correttamente la foto generata con l'IA (dopo averla ingrandita). Aurora motiva il giudizio sull'altro profilo con la "faccia" della persona. | G19: C3 | H19: =IFERROR(INDEX(Pattern!$B:$B,MATCH(G19,Pattern!$A:$A,0)),"") -> Fiducia nelle proprie capacità vs comportamenti reali
A20: S16 | B20: Intervista studentesse 07/10 | C20: Sofia, Giulia | D20: Deepfake a scuola | E20: Criterio per distinguere scherzo e cosa seria: "quando c'è uno scherzo si ride e basta", "se si fanno battute", se la vittima ride. Alla domanda sul disagio nascosto: "si capisce, dai". | F20: Estratto 2 (08:44) | G20: C4 | H20: =IFERROR(INDEX(Pattern!$B:$B,MATCH(G20,Pattern!$A:$A,0)),"") -> Deepfake e contenuti falsi tra coetanei | I20: altro possibile fallacia argomentativa. bias da eccesso di fiducia?(overconfidence bias)
A21: S17 | B21: Intervista studentesse 07/10 | C21: Aurora | D21: Deepfake a scuola | E21: Nei casi seri: parlarne "in modo discreto, senza prendere le parti e non esprirere opinioni senza conoscere a fondo la situazione. Cita un'esperienza vissuta quest'anno. | F21: Estratto 2 | G21: C4 | H21: =IFERROR(INDEX(Pattern!$B:$B,MATCH(G21,Pattern!$A:$A,0)),"") -> Deepfake e contenuti falsi tra coetanei
A22: S18 | B22: Intervista studentesse 07/10 | C22: Sofia, Chiara, Martina, Aurora | D22: Deepfake a scuola | E22: Se la vittima è in difficoltà: "vado da lei e ci parlo io", "offriamo la nostra disponibilità", "parlerei con il prof al posto suo", "ci parlo io con chi di dovere". | F22: Estratto 2 | G22: C6 | H22: =IFERROR(INDEX(Pattern!$B:$B,MATCH(G22,Pattern!$A:$A,0)),"") -> Chiedere aiuto: a chi, e perché no | I22: mette in luce la utilità del nostro spazio forum
A23: S19 | B23: Intervista studentesse 07/10 | C23: Sofia, Aurora | D23: Deepfake a scuola | E23: Coinvolgere un adulto "dipende da quanto è grave": una presa in giro è diverso da cyberbullismo. | F23: Estratto 2 | G23: C4 | H23: =IFERROR(INDEX(Pattern!$B:$B,MATCH(G23,Pattern!$A:$A,0)),"") -> Deepfake e contenuti falsi tra coetanei | I23: anche qua si evidenzia il rischio di sottostimare il problema
A24: S20 | B24: Intervista studentesse 07/10 | C24: Tutte | D24: Esercizio 3 – chat di adescamento | E24: Non concordano sul primo messaggio sospetto: Sofia indica "sei molto più matura" / "nessuno mi capisce come te" (troppo presto); Aurora "mandami una foto" e poi "non dirlo ai tuoi"; Martina "non dirlo ai tuoi"; Aurora cambia idea più volte ("dal 5... dal 6... almeno dal 4"). | G24: C5 | H24: =IFERROR(INDEX(Pattern!$B:$B,MATCH(G24,Pattern!$A:$A,0)),"") -> Riconoscere l'adescamento e le richieste di foto | I24: si evidenzia l'importanza di includere nel training sul definire i boundaries e il rispetto per gli altri e per se stessi.
A25: S21 | B25: Intervista studentesse 07/10 | C25: Aurora, Sofia | D25: Esercizio 3 – chat di adescamento | E25: Aurora: "a me va bene se mi scrive strano", legge le lusinghe come "carenza affettiva" dell'altro. Sofia: "dopo due giorni è esagerato". | F25: Estratto 3 (13:13) | G25: C5 | H25: =IFERROR(INDEX(Pattern!$B:$B,MATCH(G25,Pattern!$A:$A,0)),"") -> Riconoscere l'adescamento e le richieste di foto
A26: S22 | B26: Intervista studentesse 07/10 | C26: Aurora, Giulia | D26: Richiesta di foto | E26: A entrambe è stata chiesta una foto da qualcuno che conoscevano (per Giulia un ragazzo della stessa scuola). Aurora non l'ha mandata e l'ha bloccato. | F26: Estratto 4 (14:02) | G26: C5 | H26: =IFERROR(INDEX(Pattern!$B:$B,MATCH(G26,Pattern!$A:$A,0)),"") -> Riconoscere l'adescamento e le richieste di foto
A27: S23 | B27: Intervista studentesse 07/10 | C27: Aurora, Sofia | D27: Richiesta di foto | E27: Dopo un mese di conoscenza Aurora "magari gliela mando", "dipende che foto", anche senza essersi mai visti "se so chi è". Sofia: "solo online no", bisogna vedersi prima. Disaccordo aperto. | F27: Estratto 4 | G27: C5 | H27: =IFERROR(INDEX(Pattern!$B:$B,MATCH(G27,Pattern!$A:$A,0)),"") -> Riconoscere l'adescamento e le richieste di foto | I27: aurora potenziale utente estremo base molto inesperto
A28: S24 | B28: Intervista studentesse 07/10 | C28: Tutte | D28: Richiesta di foto | E28: Una foto a sfondo sessuale non la manderebbero a nessuno, nemmeno a persone conosciute. | F28: Estratto 4 | G28: C5 | H28: =IFERROR(INDEX(Pattern!$B:$B,MATCH(G28,Pattern!$A:$A,0)),"") -> Riconoscere l'adescamento e le richieste di foto
A29: S25 | B29: Intervista studentesse 07/10 | C29: Giulia, Martina, Sofia, Chiara | D29: Minacce | E29: Amico minacciato di diffusione di una foto: Giulia e Martina "bloccarlo e segnalarlo"; Sofia "andrei dai carabinieri"; Chiara "dal prof"; Giulia obietta "ma poi il prof vede la chat". | F29: Estratto 5 (16:43) | G29: C6 | H29: =IFERROR(INDEX(Pattern!$B:$B,MATCH(G29,Pattern!$A:$A,0)),"") -> Chiedere aiuto: a chi, e perché no
A30: S26 | B30: Intervista studentesse 07/10 | C30: Aurora | D30: Minacce | E30: "Io non voglio dirlo a mia mamma, quindi piuttosto vado dai carabinieri." | F30: Estratto 5 | G30: C6 | H30: =IFERROR(INDEX(Pattern!$B:$B,MATCH(G30,Pattern!$A:$A,0)),"") -> Chiedere aiuto: a chi, e perché no
A31: S27 | B31: Intervista studentesse 07/10 | C31: Tutte | D31: Minacce | E31: Alla domanda diretta "non ne parlereste prima con i genitori?" rispondono in coro: "prima con i genitori e poi andiamo insieme dai carabinieri". | F31: Estratto 5 | G31: C6 | H31: =IFERROR(INDEX(Pattern!$B:$B,MATCH(G31,Pattern!$A:$A,0)),"") -> Chiedere aiuto: a chi, e perché no
A32: S28 | B32: Intervista studentesse 07/10 | C32: Tutte, Aurora | D32: Minacce | E32: Se dovessero decidere da sole: "a un'amica". Aurora accenna all'IA, ma le altre su IA o forum: "no, no", "vado subito da una persona vera, per confidarmi". | F32: Estratto 5 | G32: C6 | H32: =IFERROR(INDEX(Pattern!$B:$B,MATCH(G32,Pattern!$A:$A,0)),"") -> Chiedere aiuto: a chi, e perché no | I32: ebidenziato un problema: bisogno di parlare con una persona vera --> il forum serve a questo
A33: S29 | B33: Intervista studentesse 07/10 | C33: Sofia, Giulia, tutte | D33: Forum anonimo | E33: Sofia: utile "se sei sicura che sono le persone che dicono di essere"; Giulia: "non so quanta gente riuscirebbe a dire quello che è successo". Saputo che è anonimo: tutte "ah, sì"; Giulia: "come NGL". | F33: Estratto 6 (18:37) | G33: C8 | H33: =IFERROR(INDEX(Pattern!$B:$B,MATCH(G33,Pattern!$A:$A,0)),"") -> Idea di progetto: forum anonimo e supporto | I33: giulia evidenzia il blocco a parlare di cose difficili. l'anonimità sembra dover essere un requisito del forum.
A34: S30 | B34: Intervista studentesse 07/10 | C34: Aurora | D34: Esperienza personale | E34: Alcune compagne hanno creato una chat di gruppo contro di lei con insulti e sue foto (prese da Instagram o mandate alle amiche). L'ha scoperto tramite un amico. | G34: C4 | H34: =IFERROR(INDEX(Pattern!$B:$B,MATCH(G34,Pattern!$A:$A,0)),"") -> Deepfake e contenuti falsi tra coetanei | I34: aurora si conferma utente estremo
A35: S31 | B35: Intervista studentesse 07/10 | C35: Aurora | D35: Esperienza personale | E35: Non voleva dirlo ai genitori; l'ha detto solo alle amiche, che l'hanno convinta: l'hanno detto insieme ai genitori. | G35: C6 | H35: =IFERROR(INDEX(Pattern!$B:$B,MATCH(G35,Pattern!$A:$A,0)),"") -> Chiedere aiuto: a chi, e perché no | I35: sottolinea il bisogno di una cerchia di supporto
A36: S32 | B36: Intervista studentesse 07/10 | C36: Aurora, Giulia, Martina | D36: Esperienza personale | E36: I prof si sono allarmati; i genitori sono andati in presidenza ma "il preside non ha voluto fare nulla". Giulia: "alla fine non hanno fatto abbastanza". | G36: C7 | H36: =IFERROR(INDEX(Pattern!$B:$B,MATCH(G36,Pattern!$A:$A,0)),"") -> Prevenzione e ruolo della scuola | I36: non sempre le istituzionisono in grado di rispondere: a volte si minimizza il problema o le sue conseguenze sulla vittima
A37: S33 | B37: Intervista studentesse 07/10 | C37: Aurora | D37: Esperienza personale | E37: La sua paura principale era che le foto venissero modificate con l'IA ("si può fare qualunque cosa, anche se non è vera"). Non è successo. | G37: C4 | H37: =IFERROR(INDEX(Pattern!$B:$B,MATCH(G37,Pattern!$A:$A,0)),"") -> Deepfake e contenuti falsi tra coetanei
A40: D01 | B40: Intervista docente 09/10 | C40: Docente | D40: Scuola e IA | E40: La nuova dirigente ha emanato un atto di indirizzo per regolamentare l'uso dell'IA nel PTOF; non è ancora stato attivato nulla; i docenti non sono obbligati a usarla. | G40: C7 | H40: =IFERROR(INDEX(Pattern!$B:$B,MATCH(G40,Pattern!$A:$A,0)),"") -> Prevenzione e ruolo della scuola | I40: si sottoliea la lentezza di ripsposta da parte delle istituzioni
A41: D02 | B41: Intervista docente 09/10 | C41: Docente | D41: Scuola e IA | E41: Non ha notato cambiamenti nei propri insegnamenti(matematica e fisica) né nelle relazioni tra studenti; non ha mai sentito studenti parlare di IA. | G41: C7 | H41: =IFERROR(INDEX(Pattern!$B:$B,MATCH(G41,Pattern!$A:$A,0)),"") -> Prevenzione e ruolo della scuola
A42: D03 | B42: Intervista docente 09/10 | C42: Docente | D42: Scuola e IA | E42: L'anno scorso in una classe si è tenuto un corso sull'IA; alcuni studenti si sono mostrati "parecchio ferrati". | G42: C7 | H42: =IFERROR(INDEX(Pattern!$B:$B,MATCH(G42,Pattern!$A:$A,0)),"") -> Prevenzione e ruolo della scuola
A43: D04 | B43: Intervista docente 09/10 | C43: Docente | D43: Scuola e IA | E43: Ritiene utile uno strumento educativo IA, "non solo per i ragazzi: anche per gli adulti, per tutti". | G43: C7 | H43: =IFERROR(INDEX(Pattern!$B:$B,MATCH(G43,Pattern!$A:$A,0)),"") -> Prevenzione e ruolo della scuola | I43: anche gli adulti potrebbero non essere in gr<o d idare supporto ai propri figli.
A44: D05 | B44: Intervista docente 09/10 | C44: Docente | D44: Scuola e IA | E44: Contenuto base da insegnare: l'IA può sbagliare, servono competenze per verificare quello che produce. | F44: Estratto 1 (P1 03:45) | G44: C7 | H44: =IFERROR(INDEX(Pattern!$B:$B,MATCH(G44,Pattern!$A:$A,0)),"") -> Prevenzione e ruolo della scuola
A45: D06 | B45: Intervista docente 09/10 | C45: Docente | D45: Casi a scuola | E45: Ha saputo indirettamente di una studentessa (non sua) che usava l'IA come aiuto psicologico. | F45: Estratto 2 (P1 04:38) | G45: C6 | H45: =IFERROR(INDEX(Pattern!$B:$B,MATCH(G45,Pattern!$A:$A,0)),"") -> Chiedere aiuto: a chi, e perché no
A46: D07 | B46: Intervista docente 09/10 | C46: Docente | D46: Casi a scuola | E46: Procedura: si informa il coordinatore, che informa la famiglia o parla con lo studente e cerca un aiuto specifico; il docente "prende atto" e passa "la palla a persone più competenti". | F46: Estratto 2 | G46: C7 | H46: =IFERROR(INDEX(Pattern!$B:$B,MATCH(G46,Pattern!$A:$A,0)),"") -> Prevenzione e ruolo della scuola | I46: nelle istituzioni c'è rischio di scaricabarile perché non sono sempre in grado di gestire la situazione (sperando di arrivare a qualcuno in grado), e la procedura non consente di fornire il supporto necessario.
A47: D08 | B47: Intervista docente 09/10 | C47: Docente | D47: Casi a scuola | E47: Parla direttamente con gli studenti in difficoltà, ma bisogna capire quando fermarsi e rimandare gli studenti a figure professionali. | F47: Estratto 2 | G47: C6 | H47: =IFERROR(INDEX(Pattern!$B:$B,MATCH(G47,Pattern!$A:$A,0)),"") -> Chiedere aiuto: a chi, e perché no | I47: il sopporto non necessar
A48: D09 | B48: Intervista docente 09/10 | C48: Docente | D48: Forum | E48: Un forum di condivisione sarebbe "utilissimo", "un momento di confronto". | F48: Estratto 3 (P1 06:32) | G48: C8 | H48: =IFERROR(INDEX(Pattern!$B:$B,MATCH(G48,Pattern!$A:$A,0)),"") -> Idea di progetto: forum anonimo e supporto
A49: D10 | B49: Intervista docente 09/10 | C49: Docente | D49: Spazi a scuola | E49: Le assemblee d'istituto si usano quasi solo per le elezioni; c'è la biblioteca; non esistono spazi specifici per parlare di questi temi. | G49: C7 | H49: =IFERROR(INDEX(Pattern!$B:$B,MATCH(G49,Pattern!$A:$A,0)),"") -> Prevenzione e ruolo della scuola | I49: evidenzia il bisogno di uno spazio, che potrebbe fornire il nostro progetto
A50: D11 | B50: Intervista docente 09/10 | C50: Docente | D50: Rapporto con gli studenti | E50: Con gli studenti bisogna parlare "alla pari", mai "su un piedistallo"; linguaggio "semplice e diretto"; se una cosa sembra imposta "la rigettano immediatamente". | F50: Estratto 4 (P1 09:46) | G50: C9 | H50: =IFERROR(INDEX(Pattern!$B:$B,MATCH(G50,Pattern!$A:$A,0)),"") -> Come comunicare con i ragazzi | I50: aiuto peer to peer e non top down. no imposizioni/fare didattico e istituzionale. la nostra soluzione deve uno scambio tra eguali.
A51: D12 | B51: Intervista docente 09/10 | C51: Docente | D51: Scuola e IA | E51: Il telefono a scuola è vietato del tutto (circolare ministeriale), anche per uso didattico. | G51: C7 | H51: =IFERROR(INDEX(Pattern!$B:$B,MATCH(G51,Pattern!$A:$A,0)),"") -> Prevenzione e ruolo della scuola
A52: D13 | B52: Intervista docente 09/10 | C52: Docente | D52: Genitori e adulti | E52: anche gli adulti non sono preparati. Secondo lui si parla poco di contenuti ai-positive nei media tradizionali, e troppo con toni catastrofici. Non si parla di altri rischi più comuni. | G52: C7 | H52: =IFERROR(INDEX(Pattern!$B:$B,MATCH(G52,Pattern!$A:$A,0)),"") -> Prevenzione e ruolo della scuola | I52: la nostra soluziione è utile perchè nemmeno gli adulti sanno come affrontare il problema e i ragazzi non sanno a chi chiedere aiuto su come inoformarsi.
A53: D14 | B53: Intervista docente 09/10 | C53: Docente | D53: Deepfake | E53: Davanti a un deepfake di una studentessa: chiederebbe se i genitori lo sanno, li convocherebbe e indicherebbe la polizia postale. | F53: Estratto 5 (P1 17:11) | G53: C6 | H53: =IFERROR(INDEX(Pattern!$B:$B,MATCH(G53,Pattern!$A:$A,0)),"") -> Chiedere aiuto: a chi, e perché no
A54: D15 | B54: Intervista docente 09/10 | C54: Docente | D54: Deepfake | E54: Secondo lui le ragazze non ne parlano coi genitori per il tabù sul sesso, la vergogna e la paura di rimproveri o punizioni; il dialogo in famiglia "si è perso". (Opinione, non osservazione diretta.) | F54: Estratto 6 (P1 18:17) | G54: C6 | H54: =IFERROR(INDEX(Pattern!$B:$B,MATCH(G54,Pattern!$A:$A,0)),"") -> Chiedere aiuto: a chi, e perché no
A55: D16 | B55: Intervista docente 09/10 | C55: Docente | D55: Deepfake | E55: Se la studentessa non volesse coinvolgere i genitori, la indirizzerebbe a denunciare e potrebbe accompagnarla alla polizia postale. | F55: Estratto 6 | G55: C6 | H55: =IFERROR(INDEX(Pattern!$B:$B,MATCH(G55,Pattern!$A:$A,0)),"") -> Chiedere aiuto: a chi, e perché no | I55: viene indicata una via alternativa di aiuto fuori dal cerchio familiare.
A56: D17 | B56: Intervista docente 09/10 | C56: Docente | D56: Chiedere aiuto | E56: La difficoltà maggiore è chiedere aiuto, per vergogna e per il "sentirsi sbagliati"; paragone con la violenza sessuale: "violenza a tutti gli effetti, anche quella virtuale". | F56: Estratto 7 (P1 21:07) | G56: C6 | H56: =IFERROR(INDEX(Pattern!$B:$B,MATCH(G56,Pattern!$A:$A,0)),"") -> Chiedere aiuto: a chi, e perché no
A57: D18 | B57: Intervista docente 09/10 | C57: Docente | D57: Rapporto con gli studenti | E57: Esempio: uno studente in difficoltà si è aperto dopo una semplice domanda amichevole in corridoio; servono osservazione ed empatia. | G57: C9 | H57: =IFERROR(INDEX(Pattern!$B:$B,MATCH(G57,Pattern!$A:$A,0)),"") -> Come comunicare con i ragazzi | I57: è importante trovare una persona empatica a cui chiedere aiuto.
A58: D19 | B58: Intervista docente 09/10 | C58: Docente | D58: Forum | E58: La mancanza di contatto umano di una piattaforma può essere compensata dal forum: confrontandosi tra pari "ti senti già meno solo". | F58: Estratto 8 (P1 25:37) | G58: C8 | H58: =IFERROR(INDEX(Pattern!$B:$B,MATCH(G58,Pattern!$A:$A,0)),"") -> Idea di progetto: forum anonimo e supporto
A59: D20 | B59: Intervista docente 09/10 | C59: Docente | D59: Forum | E59: Il forum va supervisionato (filtri, un supervisore) per non farlo degenerare: qualcuno che osservi senza interagire e possa "lanciare l'allarme". Avverte: "se capiscono che sono controllati..." | F59: Estratto 9 (P2 00:02) | G59: C8 | H59: =IFERROR(INDEX(Pattern!$B:$B,MATCH(G59,Pattern!$A:$A,0)),"") -> Idea di progetto: forum anonimo e supporto | I59: viene evidenziato un tema motlo delicato che dovremo risolvere in modo soddisfacente.
A60: D21 | B60: Intervista docente 09/10 | C60: Docente | D60: Forum | E60: Esperti (prof, psicologi) da contattare volontariamente tramite app: il prof si dimostra d'accordo ("esatto perfetto, mettete un team di esperti") | F60: Estratto 9 | G60: C8 | H60: =IFERROR(INDEX(Pattern!$B:$B,MATCH(G60,Pattern!$A:$A,0)),"") -> Idea di progetto: forum anonimo e supporto | I60: supporto alla nostra idea. possibile rimando a un altra app tipo unobravo.
A61: D22 | B61: Intervista docente 09/10 | C61: Docente | D61: Piattaforma | E61: Sulla sezione di training proposta dal gruppo: "perfetto, ci dovrebbe essere". | G61: C8 | H61: =IFERROR(INDEX(Pattern!$B:$B,MATCH(G61,Pattern!$A:$A,0)),"") -> Idea di progetto: forum anonimo e supporto | I61: di nuovo supporto alla nostra idea
A62: D23 | B62: Intervista docente 09/10 | C62: Docente | D62: Riservatezza | E62: Le esperienze devono restare nel forum (impedire gli screenshot); anonimato senza dati sensibili; chi scrive deve poter chiedere aiuto (team di esperti o numeri utili). | F62: Estratto 10 (P2 03:13) | G62: C8 | H62: =IFERROR(INDEX(Pattern!$B:$B,MATCH(G62,Pattern!$A:$A,0)),"") -> Idea di progetto: forum anonimo e supporto

Sheet Incroci
A1: Incroci tra domande (base: rispondenti con consenso)
A3: Fiducia nel riconoscere foto IA × cosa hanno fatto l'ultima volta che hanno dubitato
B4: Ha fatto qualcosa | C4: Non ha fatto niente | D4: Totale
A5: Fiducia 1-3 | B5: 7 | C5: 14 | D5: =SUM(B5:C5) -> 21
A6: Fiducia alta (4-5) | B6: 42 | C6: 35 | D6: =SUM(B6:C6) -> 77
A8: Fiducia nel riconoscere foto IA × saprebbe come agire
B9: Saper agire 1-3 | C9: Saprebbe agire (4-5) | D9: Totale
A10: Fiducia 1-3 | B10: 18 | C10: 3 | D10: =SUM(B10:C10) -> 21
A11: Fiducia alta (4-5) | B11: 41 | C11: 35 | D11: =SUM(B11:C11) -> 76
A13: Sa cos'è un deepfake × fiducia nel riconoscere foto IA
B14: Fiducia 1-3 | C14: Fiducia alta (4-5) | D14: Totale
A15: ne ho sentito parlare | B15: 5 | C15: 13 | D15: =SUM(B15:C15) -> 18
A16: no | B16: 7 | C16: 14 | D16: =SUM(B16:C16) -> 21
A17: sì, saprei spiegarlo | B17: 9 | C17: 50 | D17: =SUM(B17:C17) -> 59
A19: Genere × primo confidente
A20: Attenzione: solo 10 femmine e 4 non binari, confronto indicativo.
B21: altro | C21: amico o amica | D21: fratello o sorella | E21: genitore | F21: nessuno | G21: Totale
A22: Femmina | B22: 0 | C22: 9 | D22: 0 | E22: 1 | F22: 0 | G22: =SUM(B22:F22) -> 10
A23: Maschio | B23: 10 | C23: 41 | D23: 6 | E23: 9 | F23: 15 | G23: =SUM(B23:F23) -> 81
A24: Non binario | B24: 1 | C24: 1 | D24: 1 | E24: 0 | F24: 1 | G24: =SUM(B24:F24) -> 4
A25: Preferisco non rispondere | B25: 0 | C25: 0 | D25: 0 | E25: 0 | F25: 1 | G25: =SUM(B25:F25) -> 1
A27: Età × come viene considerato un deepfake tra coetanei
B28: Come un semplice scherzo per farsi una risata | C28: Come una cosa seria e potenzialmente dannosa | D28: Dipende da quanto è pesante o imbarazzante il contenuto | E28: Non ci facciamo troppo caso o non saprei | F28: Totale
A29: 14 | B29: 1 | C29: 0 | D29: 7 | E29: 3 | F29: =SUM(B29:E29) -> 11
A30: 15 | B30: 5 | C30: 1 | D30: 19 | E30: 2 | F30: =SUM(B30:E30) -> 27
A31: 16 | B31: 15 | C31: 1 | D31: 12 | E31: 4 | F31: =SUM(B31:E31) -> 32
A32: 17 | B32: 14 | C32: 2 | D32: 10 | E32: 2 | F32: =SUM(B32:E32) -> 28

Sheet Leggimi
A1: Needfinding in classe - analisi delle risposte
A2: Progetto HCI "Chi c'è dall'altra parte?" - attività in una classe di liceo (focus group a squadre)
A4: Fonti analizzate
A5: Fonte | B5: Contenuto
A6: Schede di lavoro (5 squadre) | B6: Tontony (5), Divo (5), Biscotto (4), Team Pasqua (5), Dream Team (4): 23 studenti in totale. Fasi 0, 1, 1bis, 2 e risposte alla tavola rotonda (TR1-TR4).
A7: Appunti di osservazione del team | B7: Note prese seguendo i gruppi durante la Fase 2 (chat). Codici OSS-01 ... OSS-28.
A8: Presentazione in classe | B8: Struttura dell'attività: Sfida reale vs IA, Tavola rotonda, Co-design. Da qui le soluzioni delle coppie della Fase 1bis.
A9: Soluzioni del quiz foto | B9: Fornite dal team: L0 V,F,F - L1 F,V,V - L2 V,V,F - L3 F,V,F - L4 tutte generate con l'IA.
A11: Codici usati in tutti i documenti (tracciabilità)
A12: Codice | B12: Significato
A13: TON, DIV, BIS, PAS, DRE | B13: Squadre: Tontony, Divo, Biscotto, Team Pasqua, Dream Team
A14: F0 | B14: Fase 0 - autovalutazione individuale (voto 1-10)
A15: F1-Lx-Fy | B15: Fase 1 - quiz foto, livello x, foto y (es. F1-L4-F3)
A16: F1bis-A/B/C | B16: Fase 1bis - coppie di foto (quale è stata generata dall'altra)
A17: CH-[squadra]-Cx | B17: Note scritte dalla squadra sulla chat x (es. CH-DRE-C4)
A18: OSS-nn | B18: Appunti di osservazione del team
A19: TR1...TR4-[squadra] | B19: Risposta della squadra alla domanda n della tavola rotonda (es. TR4-BIS)
A20: B1...B8 | B20: Bisogni consolidati (vedi foglio 'Analisi tematica' e documento dei bisogni)
A22: Convenzioni e limiti della trascrizione
A23: • | B23: Le schede sono scritte a mano: dove la lettura è incerta il testo è segnato con [lettura incerta].
A24: • | B24: Risposte con caselle segnate in modo contraddittorio sono marcate '?' ed escluse dai punteggi (colonna 'Esito' = n.v.).
A25: • | B25: Tontony ha compilato i livelli 3-4 sia in tabella sia su un foglio aggiunto: dove i due non coincidono vale il dato marcato '?'.
A26: • | B26: Biscotto non ha cerchiato la difficoltà; alcune squadre non hanno compilato la Fase 1bis-C e la Chat 6.
A27: • | B27: Le domande della Chat 2 e della Chat 6 non sono state discusse negli appunti: i dati su quelle chat sono solo quelli delle schede.
A28: • | B28: I numeri sono piccoli (5 squadre, 23 studenti): le percentuali servono a leggere tendenze, non hanno valore statistico.
A30: Fogli del file
A31: Foglio | B31: Contenuto
A32: Sintesi | B32: Analisi complessiva: numeri chiave, grafici, punti comuni, divergenze, sorprese
A33: F0 Autovalutazione | B33: Voti individuali e medie per squadra
A34: F1 Foto (dati) | B34: Ogni risposta del quiz foto con esito calcolato, difficoltà e indizio dichiarato
A35: F1 Foto (matrice) | B35: Risposte per foto e squadra, con quante squadre hanno indovinato
A36: F1bis Coppie | B36: Coppie di foto: quale è generata e com'è la foto rimasta
A37: Indizi usati | B37: Su cosa si basano i ragazzi per dire 'è IA' e quanto quell'indizio li porta alla risposta giusta
A38: F2 Chat | B38: Giudizio sulle chat, note dei gruppi e osservazioni del team
A39: Tavola rotonda | B39: Risposte TR1-TR4 per squadra con punti comuni e divergenze
A40: Appunti osservazione | B40: Appunti del team codificati per tema
A41: Analisi tematica | B41: Temi emersi, evidenze, convergenze/divergenze e bisogno collegato

Sheet Sintesi
A1: Sintesi complessiva
A2: I numeri sono calcolati dagli altri fogli; i testi sono l'analisi del team
A4: Numeri chiave
A5: Indicatore | B5: Valore
A6: Studenti coinvolti | B6: ='F0 Autovalutazione'!B35 -> 23
A7: Autovalutazione media - riconoscere un falso (1-10) | B7: ='F0 Autovalutazione'!C35 -> 6.6086957
A8: Autovalutazione media - riconoscere adescamento (1-10) | B8: ='F0 Autovalutazione'!D35 -> 7
A9: Accuratezza quiz foto, tutti i livelli | B9: ='F1 Foto (dati)'!E93 -> 0.79487179
A10: Accuratezza livelli 0-1 | B10: =('F1 Foto (dati)'!D97+'F1 Foto (dati)'!D98)/('F1 Foto (dati)'!C97+'F1 Foto (dati)'!C98) -> 0.93333333
A11: Accuratezza livello 4 | B11: ='F1 Foto (dati)'!E101 -> 0.52631579
A12: Foto IA non riconosciute (falsi negativi) | B12: ='F1 Foto (dati)'!G93 -> 11
A13: Foto reali giudicate IA (falsi positivi) | B13: ='F1 Foto (dati)'!F93 -> 5
A14: Chat giudicate sospette all'unanimità (su 5) | B14: =COUNTIF('F2 Chat'!G5:G9,5) -> 0
A16: Autovalutazione e risultato reale per squadra
A17: Squadra | B17: Autovalutazione foto (media /10) | C17: Autovalutazione in % | D17: Accuratezza quiz (tutti i livelli) | E17: Accuratezza livello 4 | F17: Scarto L4 - autovalutazione
A18: Tontony | B18: ='F0 Autovalutazione'!C30 -> 6.8 | C18: =B18/10 -> 0.68 | D18: ='F1 Foto (dati)'!E88 -> 0.86666667 | E18: =COUNTIFS('F1 Foto (dati)'!$B$5:$B$84,A18,'F1 Foto (dati)'!$C$5:$C$84,"L4",'F1 Foto (dati)'!$G$5:$G$84,1)/COUNTIFS('F1 Foto (dati)'!$B$5:$B$84,A18,'F1 Foto (dati)'!$C$5:$C$84,"L4",'F1 Foto (dati)'!$G$5:$G$84,"<>n.v.") -> 0.66666667 | F18: =E18-C18 -> -0.013333333
A19: Divo | B19: ='F0 Autovalutazione'!C31 -> 7 | C19: =B19/10 -> 0.7 | D19: ='F1 Foto (dati)'!E89 -> 0.8125 | E19: =COUNTIFS('F1 Foto (dati)'!$B$5:$B$84,A19,'F1 Foto (dati)'!$C$5:$C$84,"L4",'F1 Foto (dati)'!$G$5:$G$84,1)/COUNTIFS('F1 Foto (dati)'!$B$5:$B$84,A19,'F1 Foto (dati)'!$C$5:$C$84,"L4",'F1 Foto (dati)'!$G$5:$G$84,"<>n.v.") -> 0.5 | F19: =E19-C19 -> -0.2
A20: Biscotto | B20: ='F0 Autovalutazione'!C32 -> 6.5 | C20: =B20/10 -> 0.65 | D20: ='F1 Foto (dati)'!E90 -> 0.6875 | E20: =COUNTIFS('F1 Foto (dati)'!$B$5:$B$84,A20,'F1 Foto (dati)'!$C$5:$C$84,"L4",'F1 Foto (dati)'!$G$5:$G$84,1)/COUNTIFS('F1 Foto (dati)'!$B$5:$B$84,A20,'F1 Foto (dati)'!$C$5:$C$84,"L4",'F1 Foto (dati)'!$G$5:$G$84,"<>n.v.") -> 0.25 | F20: =E20-C20 -> -0.4
A21: Team Pasqua | B21: ='F0 Autovalutazione'!C33 -> 6 | C21: =B21/10 -> 0.6 | D21: ='F1 Foto (dati)'!E91 -> 0.8125 | E21: =COUNTIFS('F1 Foto (dati)'!$B$5:$B$84,A21,'F1 Foto (dati)'!$C$5:$C$84,"L4",'F1 Foto (dati)'!$G$5:$G$84,1)/COUNTIFS('F1 Foto (dati)'!$B$5:$B$84,A21,'F1 Foto (dati)'!$C$5:$C$84,"L4",'F1 Foto (dati)'!$G$5:$G$84,"<>n.v.") -> 0.75 | F21: =E21-C21 -> 0.15
A22: Dream Team | B22: ='F0 Autovalutazione'!C34 -> 6.75 | C22: =B22/10 -> 0.675 | D22: ='F1 Foto (dati)'!E92 -> 0.8 | E22: =COUNTIFS('F1 Foto (dati)'!$B$5:$B$84,A22,'F1 Foto (dati)'!$C$5:$C$84,"L4",'F1 Foto (dati)'!$G$5:$G$84,1)/COUNTIFS('F1 Foto (dati)'!$B$5:$B$84,A22,'F1 Foto (dati)'!$C$5:$C$84,"L4",'F1 Foto (dati)'!$G$5:$G$84,"<>n.v.") -> 0.5 | F22: =E22-C22 -> -0.175
A23: Lettura | B23: Sul totale le squadre fanno meglio di quanto dichiarano, perché molte foto erano facili. Ma la fiducia dichiarata (6-7/10) non cambia con la difficoltà: al livello 4, cioè con contenuti realistici come quelli che un adescatore userebbe, quattro squadre su cinque scendono sotto la propria autovalutazione. La squadra più prudente (Team Pasqua) è l'unica che al livello 4 supera il proprio voto; Biscotto, tra le più sicure sulle chat, è quella che sbaglia di più.
A25: Accuratezza per livello
A26: Livello | B26: Accuratezza
A27: Livello 0 | B27: ='F1 Foto (dati)'!E97 -> 1 | C27: estremamente facile
A28: Livello 1 | B28: ='F1 Foto (dati)'!E98 -> 0.86666667 | C28: facile
A29: Livello 2 | B29: ='F1 Foto (dati)'!E99 -> 0.8 | C29: medio
A30: Livello 3 | B30: ='F1 Foto (dati)'!E100 -> 0.85714286 | C30: difficile
A31: Livello 4 | B31: ='F1 Foto (dati)'!E101 -> 0.52631579 | C31: molto difficile
A33: Analisi complessiva
A34: Punti comuni | B34: • Tutte le squadre riconoscono senza fatica le foto facili e le richieste esplicite in chat (foto, dati personali, cambio di app, 'vieni da sola'). • Si sentono 'abbastanza' capaci (voti tra 6 e 8) e basano il giudizio su dettagli visivi ('troppo perfetto', sfondo) e su segnali sociali (amici in comune, storie, averlo visto a scuola). • Nessuno manderebbe la foto richiesta in Chat 5; la reazione più citata è bloccare o smettere di rispondere. • Tutte le squadre descrivono una difficoltà a parlarne con gli adulti (paura del giudizio, delle conseguenze, di perdere libertà). • L'attività è piaciuta perché attiva: chiedono strumenti interattivi e non 'la solita lezione'.
A35: Divergenze | B35: • Chat 1, 2 e 3 dividono le squadre: le stesse conversazioni sono 'normali' per alcuni e sospette per altri, segno che i segnali iniziali non sono condivisi. • Deepfake nel gruppo (Chat 5.1): da 'non si fa mai' a 'è solo uno scherzo', anche quando la vittima chiede di togliere la foto. • A chi chiedere aiuto: genitori (PAS, OSS-22), prima sorella/amica e poi genitori (OSS-20), polizia postale saltando i genitori (OSS-18). • Forum: leggere sì, scrivere poco; i commenti piacciono solo se moderati, una squadra non condividerebbe nulla di personale. • Tutor: utilissimo per Divo, inutile per Team Pasqua (meglio qualcuno che ti conosce), ponte verso i genitori per Dream Team.
A36: Sorprese (momenti da approfondire) | B36: • Una foto del livello 4 non è stata riconosciuta da nessuna squadra e la coppia A (doppia manipolazione) ha ingannato due squadre: al livello 4 quattro squadre su cinque restano sotto la propria autovalutazione. • Una foto viene creduta reale 'perché la faccia sembra conosciuta': la familiarità abbassa le difese. • 'Se lo conosco da un po' ci può stare' e nessuno chiede prove dell'identità: la fiducia costruita nel tempo è il punto debole, ed è proprio la strategia dell'adescatore. • Le foto reali con filtri vengono scambiate per IA: il sospetto generico non coincide con la capacità di riconoscere.
A37: Implicazioni per i bisogni | B37: • I cinque bisogni già individuati sono confermati dai dati (B1-B5), con alcune precisazioni: B1 descrive soprattutto il 'come' (modalità), B2 deve garantire anonimato e moderazione, B3 deve includere i segnali graduali. • Emergono tre bisogni nuovi: B6 verificare chi c'è dall'altra parte, B7 poter coinvolgere un adulto senza paura, B8 capire quando un contenuto manipolato smette di essere uno scherzo. • Candidati per i 3-4 bisogni da selezionare: B4, B6, B7, B8 (evidenze più forti e meno coperti da strumenti esistenti), con B1 e B2 come requisiti trasversali su come il servizio coinvolge i ragazzi.

Sheet F0 Autovalutazione
A1: Fase 0 - Quanto vi sentite capaci? (voto individuale 1-10)
A4: Squadra | B4: Componente | C4: Riconoscere foto/contenuto falso | D4: Riconoscere adescamento in chat | E4: Nota
A5: Tontony | B5: A | C5: 7 | D5: 8
A6: Tontony | B6: B | C6: 6 | D6: 8
A7: Tontony | B7: C | C7: 6 | D7: 7
A8: Tontony | B8: D | C8: 7 | D8: 9
A9: Tontony | B9: E | C9: 8 | D9: 8
A10: Divo | B10: A | C10: 7 | D10: 8
A11: Divo | B11: B | C11: 7 | D11: 8
A12: Divo | B12: C | C12: 7 | D12: 7
A13: Divo | B13: D | C13: 8 | D13: 7
A14: Divo | B14: E | C14: 6 | D14: 7
A15: Biscotto | B15: A | C15: 7 | D15: 7
A16: Biscotto | B16: B | C16: 7 | D16: 8
... A25: Dream Team | B25: B | C25: 7 | D25: 5
A26: Dream Team | B26: C | C26: 7 | E26: Componente C: cerchiati sia 3 sia 8 nella colonna chat (valore escluso dalla media)
A27: Dream Team | B27: D | C27: 4 | D27: 6
A29: Squadra | B29: N. studenti | C29: Media foto | D29: Media chat | E29: Differenza chat - foto
A30: Tontony | B30: =COUNTIF($A$5:$A$27,A30) -> 5 | C30: =AVERAGEIF($A$5:$A$27,A30,$C$5:$C$27) -> 6.8 | D30: =AVERAGEIF($A$5:$A$27,A30,$D$5:$D$27) -> 8 | E30: =D30-C30 -> 1.2
A31: Divo | B31: =COUNTIF($A$5:$A$27,A31) -> 5 | C31: =AVERAGEIF($A$5:$A$27,A31,$C$5:$C$27) -> 7 | D31: =AVERAGEIF($A$5:$A$27,A31,$D$5:$D$27) -> 7.4 | E31: =D31-C31 -> 0.4
A32: Biscotto | B32: =COUNTIF($A$5:$A$27,A32) -> 4 | C32: =AVERAGEIF($A$5:$A$27,A32,$C$5:$C$27) -> 6.5 | D32: =AVERAGEIF($A$5:$A$27,A32,$D$5:$D$27) -> 8 | E32: =D32-C32 -> 1.5
A33: Team Pasqua | B33: =COUNTIF($A$5:$A$27,A33) -> 5 | C33: =AVERAGEIF($A$5:$A$27,A33,$C$5:$C$27) -> 6 | D33: =AVERAGEIF($A$5:$A$27,A33,$D$5:$D$27) -> 5.4 | E33: =D33-C33 -> -0.6
A34: Dream Team | B34: =COUNTIF($A$5:$A$27,A34) -> 4 | C34: =AVERAGEIF($A$5:$A$27,A34,$C$5:$C$27) -> 6.75 | D34: =AVERAGEIF($A$5:$A$27,A34,$D$5:$D$27) -> 6 | E34: =D34-C34 -> -0.75
A35: Totale classe | B35: =COUNTA($A$5:$A$27) -> 23 | C35: =AVERAGE($C$5:$C$27) -> 6.6086957 | D35: =AVERAGE($D$5:$D$27) -> 7 | E35: =D35-C35 -> 0.39130435
A37: Lettura | B37: Quasi tutti si collocano tra 6 e 8 su entrambe le abilità: nessuno si sente incapace, pochi si sentono sicurissimi. Ci si sente più capaci a riconoscere l'adescamento che a riconoscere un falso, tranne in Team Pasqua, che è la squadra più prudente su entrambe. I voti in blu sono dati trascritti dalle schede.

Sheet F1 Foto (dati)
A1: Fase 1 - Reale vs IA: tutte le risposte
A2: Esito = 1 se la risposta coincide con la soluzione, 0 se no, n.v. se la risposta è ambigua
A4: Chiave | B4: Squadra | C4: Livello | D4: Foto | E4: Soluzione | F4: Risposta squadra | G4: Esito | H4: Difficoltà percepita (1-5) | I4: Indizio dichiarato | J4: Nota di trascrizione
A5: TON|L0|1 | B5: Tontony | C5: L0 | D5: 1 | E5: Reale | F5: Reale | G5: =IF(F5="?","n.v.",IF(F5=E5,1,0)) -> 1 | H5: 1
A6: TON|L0|2 | B6: Tontony | C6: L0 | D6: 2 | E6: IA | F6: IA | G6: =IF(F6="?","n.v.",IF(F6=E6,1,0)) -> 1 | H6: 1
A7: TON|L0|3 | B7: Tontony | C7: L0 | D7: 3 | E7: IA | F7: IA | G7: =IF(F7="?","n.v.",IF(F7=E7,1,0)) -> 1 | H7: 1 | I7: Non esiste tra le vesti papali
A8: TON|L1|1 | B8: Tontony | C8: L1 | D8: 1 | E8: IA | F8: IA | G8: =IF(F8="?","n.v.",IF(F8=E8,1,0)) -> 1 | H8: 1 | I8: Muscolatura del collo estrema: se allenasse il collo sarebbe anche più largo
A9: TON|L1|2 | B9: Tontony | C9: L1 | D9: 2 | E9: Reale | F9: Reale | G9: =IF(F9="?","n.v.",IF(F9=E9,1,0)) -> 1 | H9: 2
A10: TON|L1|3 | B10: Tontony | C10: L1 | D10: 3 | E10: Reale | F10: Reale | G10: =IF(F10="?","n.v.",IF(F10=E10,1,0)) -> 1 | H10: 2
A11: TON|L2|1 | B11: Tontony | C11: L2 | D11: 1 | E11: Reale | F11: IA | G11: =IF(F11="?","n.v.",IF(F11=E11,1,0)) -> 0 | H11: 4 | I11: Differenziazioni nello sfondo secondario
A12: TON|L2|2 | B12: Tontony | C12: L2 | D12: 2 | E12: Reale | F12: Reale | G12: =IF(F12="?","n.v.",IF(F12=E12,1,0)) -> 1
A13: TON|L2|3 | B13: Tontony | C13: L2 | D13: 3 | E13: IA | F13: IA | G13: =IF(F13="?","n.v.",IF(F13=E13,1,0)) -> 1 | I13: Tratti somatici modificati
A14: TON|L3|1 | B14: Tontony | C14: L3 | D14: 1 | E14: IA | F14: IA | G14: =IF(F14="?","n.v.",IF(F14=E14,1,0)) -> 1 | H14: 5 | J14: Dal foglio aggiuntivo
A15: TON|L3|2 | B15: Tontony | C15: L3 | D15: 2 | E15: Reale | F15: Reale | G15: =IF(F15="?","n.v.",IF(F15=E15,1,0)) -> 1 | H15: 5 | J15: Dal foglio aggiuntivo
A16: TON|L3|3 | B16: Tontony | C16: L3 | D16: 3 | E16: IA | F16: IA | G16: =IF(F16="?","n.v.",IF(F16=E16,1,0)) -> 1 | H16: 5 | I16: Presenza di filtri | J16: Dal foglio aggiuntivo (corretto da No a Si)
A17: TON|L4|1 | B17: Tontony | C17: L4 | D17: 1 | E17: IA | F17: IA | G17: =IF(F17="?","n.v.",IF(F17=E17,1,0)) -> 1 | H17: 5 | I17: Contrasto elevato | J17: Corretto da No a Si nel foglio aggiuntivo
A18: TON|L4|2 | B18: Tontony | C18: L4 | D18: 2 | E18: IA | F18: ? | G18: =IF(F18="?","n.v.",IF(F18=E18,1,0)) -> n.v. | H18: 5 | I18: Saturazione dei colori | J18: Tabella: No / foglio aggiuntivo: Si - escluso dal punteggio
A19: TON|L4|3 | B19: Tontony | C19: L4 | D19: 3 | E19: IA | F19: Reale | G19: =IF(F19="?","n.v.",IF(F19=E19,1,0)) -> 0
A20: TON|L4|4 | B20: Tontony | C20: L4 | D20: 4 | E20: IA | F20: IA | G20: =IF(F20="?","n.v.",IF(F20=E20,1,0)) -> 1 | H20: 5 | I20: Persone sullo sfondo secondario irreali
A21: DIV|L0|1 | B21: Divo | C21: L0 | D21: 1 | E21: Reale | F21: Reale | G21: =IF(F21="?","n.v.",IF(F21=E21,1,0)) -> 1 | H21: 1
A22: DIV|L0|2 | B22: Divo | C22: L0 | D22: 2 | E22: IA | F22: IA | G22: =IF(F22="?","n.v.",IF(F22=E22,1,0)) -> 1 | H22: 1
A23: DIV|L0|3 | B23: Divo | C23: L0 | D23: 3 | E23: IA | F23: IA | G23: =IF(F23="?","n.v.",IF(F23=E23,1,0)) -> 1 | H23: 1
A24: DIV|L1|1 | B24: Divo | C24: L1 | D24: 1 | E24: IA | F24: IA | G24: =IF(F24="?","n.v.",IF(F24=E24,1,0)) -> 1 | H24: 1 | I24: Bambolina di porcellana
A25: DIV|L1|2 | B25: Divo | C25: L1 | D25: 2 | E25: Reale | F25: Reale | G25: =IF(F25="?","n.v.",IF(F25=E25,1,0)) -> 1 | H25: 2
A26: DIV|L1|3 | B26: Divo | C26: L1 | D26: 3 | E26: Reale | F26: Reale | G26: =IF(F26="?","n.v.",IF(F26=E26,1,0)) -> 1 | H26: 5
A27: DIV|L2|1 | B27: Divo | C27: L2 | D27: 1 | E27: Reale | F27: IA | G27: =IF(F27="?","n.v.",IF(F27=E27,1,0)) -> 0 | H27: 4 | I27: Pelle perfettissima, sfondo strano
A28: DIV|L2|2 | B28: Divo | C28: L2 | D28: 2 | E28: Reale | F28: Reale | G28: =IF(F28="?","n.v.",IF(F28=E28,1,0)) -> 1 | H28: 1
A29: DIV|L2|3 | B29: Divo | C29: L2 | D29: 3 | E29: IA | F29: IA | G29: =IF(F29="?","n.v.",IF(F29=E29,1,0)) -> 1 | H29: 2 | I29: Troppo "perfetta"
A30: DIV|L3|1 | B30: Divo | C30: L3 | D30: 1 | E30: IA | F30: IA | G30: =IF(F30="?","n.v.",IF(F30=E30,1,0)) -> 1 | H30: 4 | I30: Occhi e luce degli occhi surreale
A31: DIV|L3|2 | B31: Divo | C31: L3 | D31: 2 | E31: Reale | F31: Reale | G31: =IF(F31="?","n.v.",IF(F31=E31,1,0)) -> 1 | H31: 1
A32: DIV|L3|3 | B32: Divo | C32: L3 | D32: 3 | E32: IA | F32: IA | G32: =IF(F32="?","n.v.",IF(F32=E32,1,0)) -> 1 | H32: 2 | I32: Tratti e ombre surreali
A33: DIV|L4|1 | B33: Divo | C33: L4 | D33: 1 | E33: IA | F33: IA | G33: =IF(F33="?","n.v.",IF(F33=E33,1,0)) -> 1 | H33: 5 | I33: Mignolo strano
A34: DIV|L4|2 | B34: Divo | C34: L4 | D34: 2 | E34: IA | F34: Reale | G34: =IF(F34="?","n.v.",IF(F34=E34,1,0)) -> 0 | H34: 5
A35: DIV|L4|3 | B35: Divo | C35: L4 | D35: 3 | E35: IA | F35: Reale | G35: =IF(F35="?","n.v.",IF(F35=E35,1,0)) -> 0 | H35: 5
A36: DIV|L4|4 | B36: Divo | C36: L4 | D36: 4 | E36: IA | F36: IA | G36: =IF(F36="?","n.v.",IF(F36=E36,1,0)) -> 1 | H36: 5 | I36: Amica dietro strana
A37: BIS|L0|1 | B37: Biscotto | C37: L0 | D37: 1 | E37: Reale | F37: Reale | G37: =IF(F37="?","n.v.",IF(F37=E37,1,0)) -> 1
A38: BIS|L0|2 | B38: Biscotto | C38: L0 | D38: 2 | E38: IA | F38: IA | G38: =IF(F38="?","n.v.",IF(F38=E38,1,0)) -> 1
A39: BIS|L0|3 | B39: Biscotto | C39: L0 | D39: 3 | E39: IA | F39: IA | G39: =IF(F39="?","n.v.",IF(F39=E39,1,0)) -> 1 | I39: Come è vestito il Papa
A40: BIS|L1|1 | B40: Biscotto | C40: L1 | D40: 1 | E40: IA | F40: IA | G40: =IF(F40="?","n.v.",IF(F40=E40,1,0)) -> 1 | I40: Troppo bello, pelle perfetta
A41: BIS|L1|2 | B41: Biscotto | C41: L1 | D41: 2 | E41: Reale | F41: Reale | G41: =IF(F41="?","n.v.",IF(F41=E41,1,0)) -> 1
A42: BIS|L1|3 | B42: Biscotto | C42: L1 | D42: 3 | E42: Reale | F42: IA | G42: =IF(F42="?","n.v.",IF(F42=E42,1,0)) -> 0 | I42: Ritoccata, non falsa
A43: BIS|L2|1 | B43: Biscotto | C43: L2 | D43: 1 | E43: Reale | F43: Reale | G43: =IF(F43="?","n.v.",IF(F43=E43,1,0)) -> 1
A44: BIS|L2|2 | B44: Biscotto | C44: L2 | D44: 2 | E44: Reale | F44: Reale | G44: =IF(F44="?","n.v.",IF(F44=E44,1,0)) -> 1
A45: BIS|L2|3 | B45: Biscotto | C45: L2 | D45: 3 | E45: IA | F45: IA | G45: =IF(F45="?","n.v.",IF(F45=E45,1,0)) -> 1 | I45: Pelle perfetta, la mano e lo sfondo
A46: BIS|L3|1 | B46: Biscotto | C46: L3 | D46: 1 | E46: IA | F46: IA | G46: =IF(F46="?","n.v.",IF(F46=E46,1,0)) -> 1 | I46: Sfondo
A47: BIS|L3|2 | B47: Biscotto | C47: L3 | D47: 2 | E47: Reale | F47: Reale | G47: =IF(F47="?","n.v.",IF(F47=E47,1,0)) -> 1
A48: BIS|L3|3 | B48: Biscotto | C48: L3 | D48: 3 | E48: IA | F48: Reale | G48: =IF(F48="?","n.v.",IF(F48=E48,1,0)) -> 0 | I48: Sfondo dettagliato e faccia che sembra una conosciuta (motivo per crederla reale)
A49: BIS|L4|1 | B49: Biscotto | C49: L4 | D49: 1 | E49: IA | F49: IA | G49: =IF(F49="?","n.v.",IF(F49=E49,1,0)) -> 1
A50: BIS|L4|2 | B50: Biscotto | C50: L4 | D50: 2 | E50: IA | F50: Reale | G50: =IF(F50="?","n.v.",IF(F50=E50,1,0)) -> 0 | J50: Si barrato, No annerito: letto come correzione a No
A51: BIS|L4|3 | B51: Biscotto | C51: L4 | D51: 3 | E51: IA | F51: Reale | G51: =IF(F51="?","n.v.",IF(F51=E51,1,0)) -> 0
A52: BIS|L4|4 | B52: Biscotto | C52: L4 | D52: 4 | E52: IA | F52: Reale | G52: =IF(F52="?","n.v.",IF(F52=E52,1,0)) -> 0
A53: PAS|L0|1 | B53: Team Pasqua | C53: L0 | D53: 1 | E53: Reale | F53: Reale | G53: =IF(F53="?","n.v.",IF(F53=E53,1,0)) -> 1 | H53: 1
A54: PAS|L0|2 | B54: Team Pasqua | C54: L0 | D54: 2 | E54: IA | F54: IA | G54: =IF(F54="?","n.v.",IF(F54=E54,1,0)) -> 1 | H54: 1
A55: PAS|L0|3 | B55: Team Pasqua | C55: L0 | D55: 3 | E55: IA | F55: IA | G55: =IF(F55="?","n.v.",IF(F55=E55,1,0)) -> 1 | H55: 1
A56: PAS|L1|1 | B56: Team Pasqua | C56: L1 | D56: 1 | E56: IA | F56: IA | G56: =IF(F56="?","n.v.",IF(F56=E56,1,0)) -> 1 | H56: 2 | I56: Sembra quello di TikTok, falso
A57: PAS|L1|2 | B57: Team Pasqua | C57: L1 | D57: 2 | E57: Reale | F57: Reale | G57: =IF(F57="?","n.v.",IF(F57=E57,1,0)) -> 1 | H57: 2
A58: PAS|L1|3 | B58: Team Pasqua | C58: L1 | D58: 3 | E58: Reale | F58: IA | G58: =IF(F58="?","n.v.",IF(F58=E58,1,0)) -> 0 | H58: 3 | I58: Sembra ritoccata | J58: Entrambe le caselle segnate, 'NO' scritto accanto a No: letto come Si
A59: PAS|L2|1 | B59: Team Pasqua | C59: L2 | D59: 1 | E59: Reale | F59: IA | G59: =IF(F59="?","n.v.",IF(F59=E59,1,0)) -> 0 | H59: 3 | I59: Ha la mano in qualcosa
A60: PAS|L2|2 | B60: Team Pasqua | C60: L2 | D60: 2 | E60: Reale | F60: Reale | G60: =IF(F60="?","n.v.",IF(F60=E60,1,0)) -> 1 | H60: 3
A61: PAS|L2|3 | B61: Team Pasqua | C61: L2 | D61: 3 | E61: IA | F61: IA | G61: =IF(F61="?","n.v.",IF(F61=E61,1,0)) -> 1 | H61: 3 | I61: Si vede che non è naturale
A62: PAS|L3|1 | B62: Team Pasqua | C62: L3 | D62: 1 | E62: IA | F62: IA | G62: =IF(F62="?","n.v.",IF(F62=E62,1,0)) -> 1 | H62: 3 | I62: La porta storta
A63: PAS|L3|2 | B63: Team Pasqua | C63: L3 | D63: 2 | E63: Reale | F63: Reale | G63: =IF(F63="?","n.v.",IF(F63=E63,1,0)) -> 1 | H63: 3
A64: PAS|L3|3 | B64: Team Pasqua | C64: L3 | D64: 3 | E64: IA | F64: IA | G64: =IF(F64="?","n.v.",IF(F64=E64,1,0)) -> 1 | H64: 4 | I64: Si vede che è minimamente ritoccata
A65: PAS|L4|1 | B65: Team Pasqua | C65: L4 | D65: 1 | E65: IA | F65: IA | G65: =IF(F65="?","n.v.",IF(F65=E65,1,0)) -> 1 | H65: 5 | I65: Luce sbagliata e cose che si uniscono | J65: 'NO' scritto accanto a No: letto come Si
A66: PAS|L4|2 | B66: Team Pasqua | C66: L4 | D66: 2 | E66: IA | F66: IA | G66: =IF(F66="?","n.v.",IF(F66=E66,1,0)) -> 1 | H66: 5 | I66: Le persone dietro sono fake
A67: PAS|L4|3 | B67: Team Pasqua | C67: L4 | D67: 3 | E67: IA | F67: Reale | G67: =IF(F67="?","n.v.",IF(F67=E67,1,0)) -> 0 | H67: 4 | I67: "Non ci aspettavamo che fosse vera" | J67: Commento scritto dopo la rivelazione: la credevano vera ed è falsa
A68: PAS|L4|4 | B68: Team Pasqua | C68: L4 | D68: 4 | E68: IA | F68: IA | G68: =IF(F68="?","n.v.",IF(F68=E68,1,0)) -> 1 | H68: 5 | I68: Le persone dietro e le posizioni
A69: DRE|L0|1 | B69: Dream Team | C69: L0 | D69: 1 | E69: Reale | F69: Reale | G69: =IF(F69="?","n.v.",IF(F69=E69,1,0)) -> 1 | H69: 1
A70: DRE|L0|2 | B70: Dream Team | C70: L0 | D70: 2 | E70: IA | F70: IA | G70: =IF(F70="?","n.v.",IF(F70=E70,1,0)) -> 1 | H70: 1 | I70: Troppo perfetto
A71: DRE|L0|3 | B71: Dream Team | C71: L0 | D71: 3 | E71: IA | F71: IA | G71: =IF(F71="?","n.v.",IF(F71=E71,1,0)) -> 1 | H71: 1 | I71: Il Papa indossa un giubbotto
A72: DRE|L1|1 | B72: Dream Team | C72: L1 | D72: 1 | E72: IA | F72: IA | G72: =IF(F72="?","n.v.",IF(F72=E72,1,0)) -> 1 | H72: 2 | I72: Troppo perfetto
A73: DRE|L1|2 | B73: Dream Team | C73: L1 | D73: 2 | E73: Reale | F73: Reale | G73: =IF(F73="?","n.v.",IF(F73=E73,1,0)) -> 1 | H73: 3
A74: DRE|L1|3 | B74: Dream Team | C74: L1 | D74: 3 | E74: Reale | F74: Reale | G74: =IF(F74="?","n.v.",IF(F74=E74,1,0)) -> 1 | H74: 1
A75: DRE|L2|1 | B75: Dream Team | C75: L2 | D75: 1 | E75: Reale | F75: Reale | G75: =IF(F75="?","n.v.",IF(F75=E75,1,0)) -> 1 | H75: 4
A76: DRE|L2|2 | B76: Dream Team | C76: L2 | D76: 2 | E76: Reale | F76: Reale | G76: =IF(F76="?","n.v.",IF(F76=E76,1,0)) -> 1 | H76: 2
A77: DRE|L2|3 | B77: Dream Team | C77: L2 | D77: 3 | E77: IA | F77: IA | G77: =IF(F77="?","n.v.",IF(F77=E77,1,0)) -> 1 | H77: 3 | I77: Troppo perfetto
A78: DRE|L3|1 | B78: Dream Team | C78: L3 | D78: 1 | E78: IA | F78: Reale | G78: =IF(F78="?","n.v.",IF(F78=E78,1,0)) -> 0 | H78: 2
A79: DRE|L3|2 | B79: Dream Team | C79: L3 | D79: 2 | E79: Reale | F79: Reale | G79: =IF(F79="?","n.v.",IF(F79=E79,1,0)) -> 1 | H79: 4
A80: DRE|L3|3 | B80: Dream Team | C80: L3 | D80: 3 | E80: IA | F80: ? | G80: =IF(F80="?","n.v.",IF(F80=E80,1,0)) -> n.v. | H80: 1 | I80: Sembra un uso di filtri | J80: 'NO' scritto accanto a entrambe le caselle - escluso dal punteggio
A81: DRE|L4|1 | B81: Dream Team | C81: L4 | D81: 1 | E81: IA | F81: IA | G81: =IF(F81="?","n.v.",IF(F81=E81,1,0)) -> 1 | H81: 5 | I81: Macchia
A82: DRE|L4|2 | B82: Dream Team | C82: L4 | D82: 2 | E82: IA | F82: IA | G82: =IF(F82="?","n.v.",IF(F82=E82,1,0)) -> 1 | H82: 2 | I82: Sfondo
A83: DRE|L4|3 | B83: Dream Team | C83: L4 | D83: 3 | E83: IA | F83: Reale | G83: =IF(F83="?","n.v.",IF(F83=E83,1,0)) -> 0 | H83: 5
A84: DRE|L4|4 | B84: Dream Team | C84: L4 | D84: 4 | E84: IA | F84: Reale | G84: =IF(F84="?","n.v.",IF(F84=E84,1,0)) -> 0 | H84: 2
A86: Accuratezza per squadra
B87: Squadra | C87: Risposte valide | D87: Corrette | E87: Accuratezza | F87: Falsi positivi (reale giudicata IA) | G87: Falsi negativi (IA giudicata reale)
B88: Tontony | C88: =COUNTIFS($B$5:$B$84,B88,$G$5:$G$84,"<>n.v.") -> 15 | D88: =COUNTIFS($B$5:$B$84,B88,$G$5:$G$84,1) -> 13 | E88: =IF(C88=0,0,D88/C88) -> 0.86666667 | F88: =COUNTIFS($B$5:$B$84,B88,$E$5:$E$84,"Reale",$F$5:$F$84,"IA") -> 1 | G88: =COUNTIFS($B$5:$B$84,B88,$E$5:$E$84,"IA",$F$5:$F$84,"Reale") -> 1
B89: Divo | C89: =COUNTIFS($B$5:$B$84,B89,$G$5:$G$84,"<>n.v.") -> 16 | D89: =COUNTIFS($B$5:$B$84,B89,$G$5:$G$84,1) -> 13 | E89: =IF(C89=0,0,D89/C89) -> 0.8125 | F89: =COUNTIFS($B$5:$B$84,B89,$E$5:$E$84,"Reale",$F$5:$F$84,"IA") -> 1 | G89: =COUNTIFS($B$5:$B$84,B89,$E$5:$E$84,"IA",$F$5:$F$84,"Reale") -> 2
B90: Biscotto | C90: =COUNTIFS($B$5:$B$84,B90,$G$5:$G$84,"<>n.v.") -> 16 | D90: =COUNTIFS($B$5:$B$84,B90,$G$5:$G$84,1) -> 11 | E90: =IF(C90=0,0,D90/C90) -> 0.6875 | F90: =COUNTIFS($B$5:$B$84,B90,$E$5:$E$84,"Reale",$F$5:$F$84,"IA") -> 1 | G90: =COUNTIFS($B$5:$B$84,B90,$E$5:$E$84,"IA",$F$5:$F$84,"Reale") -> 4
B91: Team Pasqua | C91: =COUNTIFS($B$5:$B$84,B91,$G$5:$G$84,"<>n.v.") -> 16 | D91: =COUNTIFS($B$5:$B$84,B91,$G$5:$G$84,1) -> 13 | E91: =IF(C91=0,0,D91/C91) -> 0.8125 | F91: =COUNTIFS($B$5:$B$84,B91,$E$5:$E$84,"Reale",$F$5:$F$84,"IA") -> 2 | G91: =COUNTIFS($B$5:$B$84,B91,$E$5:$E$84,"IA",$F$5:$F$84,"Reale") -> 1
B92: Dream Team | C92: =COUNTIFS($B$5:$B$84,B92,$G$5:$G$84,"<>n.v.") -> 15 | D92: =COUNTIFS($B$5:$B$84,B92,$G$5:$G$84,1) -> 12 | E92: =IF(C92=0,0,D92/C92) -> 0.8 | F92: =COUNTIFS($B$5:$B$84,B92,$E$5:$E$84,"Reale",$F$5:$F$84,"IA") -> 0 | G92: =COUNTIFS($B$5:$B$84,B92,$E$5:$E$84,"IA",$F$5:$F$84,"Reale") -> 3
B93: Totale | C93: =SUM(C88:C92) -> 78 | D93: =SUM(D88:D92) -> 62 | E93: =IF(C93=0,0,D93/C93) -> 0.79487179 | F93: =SUM(F88:F92) -> 5 | G93: =SUM(G88:G92) -> 11
A95: Accuratezza per livello (tutte le squadre)
B96: Livello | C96: Risposte valide | D96: Corrette | E96: Accuratezza | F96: Difficoltà media percepita
B97: L0 | C97: =COUNTIFS($C$5:$C$84,B97,$G$5:$G$84,"<>n.v.") -> 15 | D97: =COUNTIFS($C$5:$C$84,B97,$G$5:$G$84,1) -> 15 | E97: =IF(C97=0,0,D97/C97) -> 1 | F97: =IFERROR(AVERAGEIF($C$5:$C$84,B97,$H$5:$H$84),"") -> 1
B98: L1 | C98: =COUNTIFS($C$5:$C$84,B98,$G$5:$G$84,"<>n.v.") -> 15 | D98: =COUNTIFS($C$5:$C$84,B98,$G$5:$G$84,1) -> 13 | E98: =IF(C98=0,0,D98/C98) -> 0.86666667 | F98: =IFERROR(AVERAGEIF($C$5:$C$84,B98,$H$5:$H$84),"") -> 2.1666667
B99: L2 | C99: =COUNTIFS($C$5:$C$84,B99,$G$5:$G$84,"<>n.v.") -> 15 | D99: =COUNTIFS($C$5:$C$84,B99,$G$5:$G$84,1) -> 12 | E99: =IF(C99=0,0,D99/C99) -> 0.8 | F99: =IFERROR(AVERAGEIF($C$5:$C$84,B99,$H$5:$H$84),"") -> 2.9
B100: L3 | C100: =COUNTIFS($C$5:$C$84,B100,$G$5:$G$84,"<>n.v.") -> 14 | D100: =COUNTIFS($C$5:$C$84,B100,$G$5:$G$84,1) -> 12 | E100: =IF(C100=0,0,D100/C100) -> 0.85714286 | F100: =IFERROR(AVERAGEIF($C$5:$C$84,B100,$H$5:$H$84),"") -> 3.25
B101: L4 | C101: =COUNTIFS($C$5:$C$84,B101,$G$5:$G$84,"<>n.v.") -> 19 | D101: =COUNTIFS($C$5:$C$84,B101,$G$5:$G$84,1) -> 10 | E101: =IF(C101=0,0,D101/C101) -> 0.52631579 | F101: =IFERROR(AVERAGEIF($C$5:$C$84,B101,$H$5:$H$84),"") -> 4.5333333

Sheet F1 Foto (matrice)
A1: Fase 1 - Matrice delle risposte (IA / Reale) per foto e squadra
A2: Verde = risposta corretta, rosso = errata. Le celle leggono il foglio 'F1 Foto (dati)'.
A4: Livello | B4: Foto | C4: Soluzione | D4: Tontony | E4: Divo | F4: Biscotto | G4: Team Pasqua | H4: Dream Team | I4: Squadre che indovinano | J4: Risposte valide | K4: % corrette | L4: Osservazione
A5: L0 | B5: 1 | C5: Reale | D5: =INDEX('F1 Foto (dati)'!$F$5:$F$84,MATCH("TON|L0|1",'F1 Foto (dati)'!$A$5:$A$84,0)) -> Reale | E5: =INDEX('F1 Foto (dati)'!$F$5:$F$84,MATCH("DIV|L0|1",'F1 Foto (dati)'!$A$5:$A$84,0)) -> Reale | F5: =INDEX('F1 Foto (dati)'!$F$5:$F$84,MATCH("BIS|L0|1",'F1 Foto (dati)'!$A$5:$A$84,0)) -> Reale | G5: =INDEX('F1 Foto (dati)'!$F$5:$F$84,MATCH("PAS|L0|1",'F1 Foto (dati)'!$A$5:$A$84,0)) -> Reale | H5: =INDEX('F1 Foto (dati)'!$F$5:$F$84,MATCH("DRE|L0|1",'F1 Foto (dati)'!$A$5:$A$84,0)) -> Reale | I5: =COUNTIFS('F1 Foto (dati)'!$C$5:$C$84,A5,'F1 Foto (dati)'!$D$5:$D$84,B5,'F1 Foto (dati)'!$G$5:$G$84,1) -> 5 | J5: =COUNTIFS('F1 Foto (dati)'!$C$5:$C$84,A5,'F1 Foto (dati)'!$D$5:$D$84,B5,'F1 Foto (dati)'!$G$5:$G$84,"<>n.v.") -> 5 | K5: =IF(J5=0,0,I5/J5) -> 1
A6: L0 | B6: 2 | C6: IA | D6: =INDEX('F1 Foto (dati)'!$F$5:$F$84,MATCH("TON|L0|2",'F1 Foto (dati)'!$A$5:$A$84,0)) -> IA | E6: =INDEX('F1 Foto (dati)'!$F$5:$F$84,MATCH("DIV|L0|2",'F1 Foto (dati)'!$A$5:$A$84,0)) -> IA | F6: =INDEX('F1 Foto (dati)'!$F$5:$F$84,MATCH("BIS|L0|2",'F1 Foto (dati)'!$A$5:$A$84,0)) -> IA | G6: =INDEX('F1 Foto (dati)'!$F$5:$F$84,MATCH("PAS|L0|2",'F1 Foto (dati)'!$A$5:$A$84,0)) -> IA | H6: =INDEX('F1 Foto (dati)'!$F$5:$F$84,MATCH("DRE|L0|2",'F1 Foto (dati)'!$A$5:$A$84,0)) -> IA | I6: =COUNTIFS('F1 Foto (dati)'!$C$5:$C$84,A6,'F1 Foto (dati)'!$D$5:$D$84,B6,'F1 Foto (dati)'!$G$5:$G$84,1) -> 5 | J6: =COUNTIFS('F1 Foto (dati)'!$C$5:$C$84,A6,'F1 Foto (dati)'!$D$5:$D$84,B6,'F1 Foto (dati)'!$G$5:$G$84,"<>n.v.") -> 5 | K6: =IF(J6=0,0,I6/J6) -> 1
A7: L0 | B7: 3 | C7: IA | D7: =INDEX('F1 Foto (dati)'!$F$5:$F$84,MATCH("TON|L0|3",'F1 Foto (dati)'!$A$5:$A$84,0)) -> IA | E7: =INDEX('F1 Foto (dati)'!$F$5:$F$84,MATCH("DIV|L0|3",'F1 Foto (dati)'!$A$5:$A$84,0)) -> IA | F7: =INDEX('F1 Foto (dati)'!$F$5:$F$84,MATCH("BIS|L0|3",'F1 Foto (dati)'!$A$5:$A$84,0)) -> IA | G7: =INDEX('F1 Foto (dati)'!$F$5:$F$84,MATCH("PAS|L0|3",'F1 Foto (dati)'!$A$5:$A$84,0)) -> IA | H7: =INDEX('F1 Foto (dati)'!$F$5:$F$84,MATCH("DRE|L0|3",'F1 Foto (dati)'!$A$5:$A$84,0)) -> IA | I7: =COUNTIFS('F1 Foto (dati)'!$C$5:$C$84,A7,'F1 Foto (dati)'!$D$5:$D$84,B7,'F1 Foto (dati)'!$G$5:$G$84,1) -> 5 | J7: =COUNTIFS('F1 Foto (dati)'!$C$5:$C$84,A7,'F1 Foto (dati)'!$D$5:$D$84,B7,'F1 Foto (dati)'!$G$5:$G$84,"<>n.v.") -> 5 | K7: =IF(J7=0,0,I7/J7) -> 1
A8: L1 | B8: 1 | C8: IA | D8: =INDEX('F1 Foto (dati)'!$F$5:$F$84,MATCH("TON|L1|1",'F1 Foto (dati)'!$A$5:$A$84,0)) -> IA | E8: =INDEX('F1 Foto (dati)'!$F$5:$F$84,MATCH("DIV|L1|1",'F1 Foto (dati)'!$A$5:$A$84,0)) -> IA | F8: =INDEX('F1 Foto (dati)'!$F$5:$F$84,MATCH("BIS|L1|1",'F1 Foto (dati)'!$A$5:$A$84,0)) -> IA | G8: =INDEX('F1 Foto (dati)'!$F$5:$F$84,MATCH("PAS|L1|1",'F1 Foto (dati)'!$A$5:$A$84,0)) -> IA | H8: =INDEX('F1 Foto (dati)'!$F$5:$F$84,MATCH("DRE|L1|1",'F1 Foto (dati)'!$A$5:$A$84,0)) -> IA | I8: =COUNTIFS('F1 Foto (dati)'!$C$5:$C$84,A8,'F1 Foto (dati)'!$D$5:$D$84,B8,'F1 Foto (dati)'!$G$5:$G$84,1) -> 5 | J8: =COUNTIFS('F1 Foto (dati)'!$C$5:$C$84,A8,'F1 Foto (dati)'!$D$5:$D$84,B8,'F1 Foto (dati)'!$G$5:$G$84,"<>n.v.") -> 5 | K8: =IF(J8=0,0,I8/J8) -> 1
A9: L1 | B9: 2 | C9: Reale | D9: =INDEX('F1 Foto (dati)'!$F$5:$F$84,MATCH("TON|L1|2",'F1 Foto (dati)'!$A$5:$A$84,0)) -> Reale | E9: =INDEX('F1 Foto (dati)'!$F$5:$F$84,MATCH("DIV|L1|2",'F1 Foto (dati)'!$A$5:$A$84,0)) -> Reale | F9: =INDEX('F1 Foto (dati)'!$F$5:$F$84,MATCH("BIS|L1|2",'F1 Foto (dati)'!$A$5:$A$84,0)) -> Reale | G9: =INDEX('F1 Foto (dati)'!$F$5:$F$84,MATCH("PAS|L1|2",'F1 Foto (dati)'!$A$5:$A$84,0)) -> Reale | H9: =INDEX('F1 Foto (dati)'!$F$5:$F$84,MATCH("DRE|L1|2",'F1 Foto (dati)'!$A$5:$A$84,0)) -> Reale | I9: =COUNTIFS('F1 Foto (dati)'!$C$5:$C$84,A9,'F1 Foto (dati)'!$D$5:$D$84,B9,'F1 Foto (dati)'!$G$5:$G$84,1) -> 5 | J9: =COUNTIFS('F1 Foto (dati)'!$C$5:$C$84,A9,'F1 Foto (dati)'!$D$5:$D$84,B9,'F1 Foto (dati)'!$G$5:$G$84,"<>n.v.") -> 5 | K9: =IF(J9=0,0,I9/J9) -> 1
A10: L1 | B10: 3 | C10: Reale | D10: =INDEX('F1 Foto (dati)'!$F$5:$F$84,MATCH("TON|L1|3",'F1 Foto (dati)'!$A$5:$A$84,0)) -> Reale | E10: =INDEX('F1 Foto (dati)'!$F$5:$F$84,MATCH("DIV|L1|3",'F1 Foto (dati)'!$A$5:$A$84,0)) -> Reale | F10: =INDEX('F1 Foto (dati)'!$F$5:$F$84,MATCH("BIS|L1|3",'F1 Foto (dati)'!$A$5:$A$84,0)) -> IA | G10: =INDEX('F1 Foto (dati)'!$F$5:$F$84,MATCH("PAS|L1|3",'F1 Foto (dati)'!$A$5:$A$84,0)) -> IA | H10: =INDEX('F1 Foto (dati)'!$F$5:$F$84,MATCH("DRE|L1|3",'F1 Foto (dati)'!$A$5:$A$84,0)) -> Reale | I10: =COUNTIFS('F1 Foto (dati)'!$C$5:$C$84,A10,'F1 Foto (dati)'!$D$5:$D$84,B10,'F1 Foto (dati)'!$G$5:$G$84,1) -> 3 | J10: =COUNTIFS('F1 Foto (dati)'!$C$5:$C$84,A10,'F1 Foto (dati)'!$D$5:$D$84,B10,'F1 Foto (dati)'!$G$5:$G$84,"<>n.v.") -> 5 | K10: =IF(J10=0,0,I10/J10) -> 0.6 | L10: Foto reale ma 'ritoccata': 2 squadre la segnano come IA (BIS, PAS)
A11: L2 | B11: 1 | C11: Reale | D11: =INDEX('F1 Foto (dati)'!$F$5:$F$84,MATCH("TON|L2|1",'F1 Foto (dati)'!$A$5:$A$84,0)) -> IA | E11: =INDEX('F1 Foto (dati)'!$F$5:$F$84,MATCH("DIV|L2|1",'F1 Foto (dati)'!$A$5:$A$84,0)) -> IA | F11: =INDEX('F1 Foto (dati)'!$F$5:$F$84,MATCH("BIS|L2|1",'F1 Foto (dati)'!$A$5:$A$84,0)) -> Reale | G11: =INDEX('F1 Foto (dati)'!$F$5:$F$84,MATCH("PAS|L2|1",'F1 Foto (dati)'!$A$5:$A$84,0)) -> IA | H11: =INDEX('F1 Foto (dati)'!$F$5:$F$84,MATCH("DRE|L2|1",'F1 Foto (dati)'!$A$5:$A$84,0)) -> Reale | I11: =COUNTIFS('F1 Foto (dati)'!$C$5:$C$84,A11,'F1 Foto (dati)'!$D$5:$D$84,B11,'F1 Foto (dati)'!$G$5:$G$84,1) -> 2 | J11: =COUNTIFS('F1 Foto (dati)'!$C$5:$C$84,A11,'F1 Foto (dati)'!$D$5:$D$84,B11,'F1 Foto (dati)'!$G$5:$G$84,"<>n.v.") -> 5 | K11: =IF(J11=0,0,I11/J11) -> 0.4 | L11: Foto reale giudicata IA da 3 squadre per sfondo, pelle o mano: l'indizio 'troppo perfetto' genera falsi allarmi
A12: L2 | B12: 2 | C12: Reale | D12: =INDEX('F1 Foto (dati)'!$F$5:$F$84,MATCH("TON|L2|2",'F1 Foto (dati)'!$A$5:$A$84,0)) -> Reale | E12: =INDEX('F1 Foto (dati)'!$F$5:$F$84,MATCH("DIV|L2|2",'F1 Foto (dati)'!$A$5:$A$84,0)) -> Reale | F12: =INDEX('F1 Foto (dati)'!$F$5:$F$84,MATCH("BIS|L2|2",'F1 Foto (dati)'!$A$5:$A$84,0)) -> Reale | G12: =INDEX('F1 Foto (dati)'!$F$5:$F$84,MATCH("PAS|L2|2",'F1 Foto (dati)'!$A$5:$A$84,0)) -> Reale | H12: =INDEX('F1 Foto (dati)'!$F$5:$F$84,MATCH("DRE|L2|2",'F1 Foto (dati)'!$A$5:$A$84,0)) -> Reale | I12: =COUNTIFS('F1 Foto (dati)'!$C$5:$C$84,A12,'F1 Foto (dati)'!$D$5:$D$84,B12,'F1 Foto (dati)'!$G$5:$G$84,1) -> 5 | J12: =COUNTIFS('F1 Foto (dati)'!$C$5:$C$84,A12,'F1 Foto (dati)'!$D$5:$D$84,B12,'F1 Foto (dati)'!$G$5:$G$84,"<>n.v.") -> 5 | K12: =IF(J12=0,0,I12/J12) -> 1
A13: L2 | B13: 3 | C13: IA | D13: =INDEX('F1 Foto (dati)'!$F$5:$F$84,MATCH("TON|L2|3",'F1 Foto (dati)'!$A$5:$A$84,0)) -> IA | E13: =INDEX('F1 Foto (dati)'!$F$5:$F$84,MATCH("DIV|L2|3",'F1 Foto (dati)'!$A$5:$A$84,0)) -> IA | F13: =INDEX('F1 Foto (dati)'!$F$5:$F$84,MATCH("BIS|L2|3",'F1 Foto (dati)'!$A$5:$A$84,0)) -> IA | G13: =INDEX('F1 Foto (dati)'!$F$5:$F$84,MATCH("PAS|L2|3",'F1 Foto (dati)'!$A$5:$A$84,0)) -> IA | H13: =INDEX('F1 Foto (dati)'!$F$5:$F$84,MATCH("DRE|L2|3",'F1 Foto (dati)'!$A$5:$A$84,0)) -> IA | I13: =COUNTIFS('F1 Foto (dati)'!$C$5:$C$84,A13,'F1 Foto (dati)'!$D$5:$D$84,B13,'F1 Foto (dati)'!$G$5:$G$84,1) -> 5 | J13: =COUNTIFS('F1 Foto (dati)'!$C$5:$C$84,A13,'F1 Foto (dati)'!$D$5:$D$84,B13,'F1 Foto (dati)'!$G$5:$G$84,"<>n.v.") -> 5 | K13: =IF(J13=0,0,I13/J13) -> 1
A14: L3 | B14: 1 | C14: IA | D14: =INDEX('F1 Foto (dati)'!$F$5:$F$84,MATCH("TON|L3|1",'F1 Foto (dati)'!$A$5:$A$84,0)) -> IA | E14: =INDEX('F1 Foto (dati)'!$F$5:$F$84,MATCH("DIV|L3|1",'F1 Foto (dati)'!$A$5:$A$84,0)) -> IA | F14: =INDEX('F1 Foto (dati)'!$F$5:$F$84,MATCH("BIS|L3|1",'F1 Foto (dati)'!$A$5:$A$84,0)) -> IA | G14: =INDEX('F1 Foto (dati)'!$F$5:$F$84,MATCH("PAS|L3|1",'F1 Foto (dati)'!$A$5:$A$84,0)) -> IA | H14: =INDEX('F1 Foto (dati)'!$F$5:$F$84,MATCH("DRE|L3|1",'F1 Foto (dati)'!$A$5:$A$84,0)) -> Reale | I14: =COUNTIFS('F1 Foto (dati)'!$C$5:$C$84,A14,'F1 Foto (dati)'!$D$5:$D$84,B14,'F1 Foto (dati)'!$G$5:$G$84,1) -> 4 | J14: =COUNTIFS('F1 Foto (dati)'!$C$5:$C$84,A14,'F1 Foto (dati)'!$D$5:$D$84,B14,'F1 Foto (dati)'!$G$5:$G$84,"<>n.v.") -> 5 | K14: =IF(J14=0,0,I14/J14) -> 0.8
A15: L3 | B15: 2 | C15: Reale | D15: =INDEX('F1 Foto (dati)'!$F$5:$F$84,MATCH("TON|L3|2",'F1 Foto (dati)'!$A$5:$A$84,0)) -> Reale | E15: =INDEX('F1 Foto (dati)'!$F$5:$F$84,MATCH("DIV|L3|2",'F1 Foto (dati)'!$A$5:$A$84,0)) -> Reale | F15: =INDEX('F1 Foto (dati)'!$F$5:$F$84,MATCH("BIS|L3|2",'F1 Foto (dati)'!$A$5:$A$84,0)) -> Reale | G15: =INDEX('F1 Foto (dati)'!$F$5:$F$84,MATCH("PAS|L3|2",'F1 Foto (dati)'!$A$5:$A$84,0)) -> Reale | H15: =INDEX('F1 Foto (dati)'!$F$5:$F$84,MATCH("DRE|L3|2",'F1 Foto (dati)'!$A$5:$A$84,0)) -> Reale | I15: =COUNTIFS('F1 Foto (dati)'!$C$5:$C$84,A15,'F1 Foto (dati)'!$D$5:$D$84,B15,'F1 Foto (dati)'!$G$5:$G$84,1) -> 5 | J15: =COUNTIFS('F1 Foto (dati)'!$C$5:$C$84,A15,'F1 Foto (dati)'!$D$5:$D$84,B15,'F1 Foto (dati)'!$G$5:$G$84,"<>n.v.") -> 5 | K15: =IF(J15=0,0,I15/J15) -> 1
A16: L3 | B16: 3 | C16: IA | D16: =INDEX('F1 Foto (dati)'!$F$5:$F$84,MATCH("TON|L3|3",'F1 Foto (dati)'!$A$5:$A$84,0)) -> IA | E16: =INDEX('F1 Foto (dati)'!$F$5:$F$84,MATCH("DIV|L3|3",'F1 Foto (dati)'!$A$5:$A$84,0)) -> IA | F16: =INDEX('F1 Foto (dati)'!$F$5:$F$84,MATCH("BIS|L3|3",'F1 Foto (dati)'!$A$5:$A$84,0)) -> Reale | G16: =INDEX('F1 Foto (dati)'!$F$5:$F$84,MATCH("PAS|L3|3",'F1 Foto (dati)'!$A$5:$A$84,0)) -> IA | H16: =INDEX('F1 Foto (dati)'!$F$5:$F$84,MATCH("DRE|L3|3",'F1 Foto (dati)'!$A$5:$A$84,0)) -> ? | I16: =COUNTIFS('F1 Foto (dati)'!$C$5:$C$84,A16,'F1 Foto (dati)'!$D$5:$D$84,B16,'F1 Foto (dati)'!$G$5:$G$84,1) -> 3 | J16: =COUNTIFS('F1 Foto (dati)'!$C$5:$C$84,A16,'F1 Foto (dati)'!$D$5:$D$84,B16,'F1 Foto (dati)'!$G$5:$G$84,"<>n.v.") -> 4 | K16: =IF(J16=0,0,I16/J16) -> 0.75 | L16: BIS la crede reale perché 'la faccia sembra una conosciuta': la familiarità abbassa la guardia
A17: L4 | B17: 1 | C17: IA | D17: =INDEX('F1 Foto (dati)'!$F$5:$F$84,MATCH("TON|L4|1",'F1 Foto (dati)'!$A$5:$A$84,0)) -> IA | E17: =INDEX('F1 Foto (dati)'!$F$5:$F$84,MATCH("DIV|L4|1",'F1 Foto (dati)'!$A$5:$A$84,0)) -> IA | F17: =INDEX('F1 Foto (dati)'!$F$5:$F$84,MATCH("BIS|L4|1",'F1 Foto (dati)'!$A$5:$A$84,0)) -> IA | G17: =INDEX('F1 Foto (dati)'!$F$5:$F$84,MATCH("PAS|L4|1",'F1 Foto (dati)'!$A$5:$A$84,0)) -> IA | H17: =INDEX('F1 Foto (dati)'!$F$5:$F$84,MATCH("DRE|L4|1",'F1 Foto (dati)'!$A$5:$A$84,0)) -> IA | I17: =COUNTIFS('F1 Foto (dati)'!$C$5:$C$84,A17,'F1 Foto (dati)'!$D$5:$D$84,B17,'F1 Foto (dati)'!$G$5:$G$84,1) -> 5 | J17: =COUNTIFS('F1 Foto (dati)'!$C$5:$C$84,A17,'F1 Foto (dati)'!$D$5:$D$84,B17,'F1 Foto (dati)'!$G$5:$G$84,"<>n.v.") -> 5 | K17: =IF(J17=0,0,I17/J17) -> 1
A18: L4 | B18: 2 | C18: IA | D18: =INDEX('F1 Foto (dati)'!$F$5:$F$84,MATCH("TON|L4|2",'F1 Foto (dati)'!$A$5:$A$84,0)) -> ? | E18: =INDEX('F1 Foto (dati)'!$F$5:$F$84,MATCH("DIV|L4|2",'F1 Foto (dati)'!$A$5:$A$84,0)) -> Reale | F18: =INDEX('F1 Foto (dati)'!$F$5:$F$84,MATCH("BIS|L4|2",'F1 Foto (dati)'!$A$5:$A$84,0)) -> Reale | G18: =INDEX('F1 Foto (dati)'!$F$5:$F$84,MATCH("PAS|L4|2",'F1 Foto (dati)'!$A$5:$A$84,0)) -> IA | H18: =INDEX('F1 Foto (dati)'!$F$5:$F$84,MATCH("DRE|L4|2",'F1 Foto (dati)'!$A$5:$A$84,0)) -> IA | I18: =COUNTIFS('F1 Foto (dati)'!$C$5:$C$84,A18,'F1 Foto (dati)'!$D$5:$D$84,B18,'F1 Foto (dati)'!$G$5:$G$84,1) -> 2 | J18: =COUNTIFS('F1 Foto (dati)'!$C$5:$C$84,A18,'F1 Foto (dati)'!$D$5:$D$84,B18,'F1 Foto (dati)'!$G$5:$G$84,"<>n.v.") -> 4 | K18: =IF(J18=0,0,I18/J18) -> 0.5 | L18: Divisione netta tra squadre
A19: L4 | B19: 3 | C19: IA | D19: =INDEX('F1 Foto (dati)'!$F$5:$F$84,MATCH("TON|L4|3",'F1 Foto (dati)'!$A$5:$A$84,0)) -> Reale | E19: =INDEX('F1 Foto (dati)'!$F$5:$F$84,MATCH("DIV|L4|3",'F1 Foto (dati)'!$A$5:$A$84,0)) -> Reale | F19: =INDEX('F1 Foto (dati)'!$F$5:$F$84,MATCH("BIS|L4|3",'F1 Foto (dati)'!$A$5:$A$84,0)) -> Reale | G19: =INDEX('F1 Foto (dati)'!$F$5:$F$84,MATCH("PAS|L4|3",'F1 Foto (dati)'!$A$5:$A$84,0)) -> Reale | H19: =INDEX('F1 Foto (dati)'!$F$5:$F$84,MATCH("DRE|L4|3",'F1 Foto (dati)'!$A$5:$A$84,0)) -> Reale | I19: =COUNTIFS('F1 Foto (dati)'!$C$5:$C$84,A19,'F1 Foto (dati)'!$D$5:$D$84,B19,'F1 Foto (dati)'!$G$5:$G$84,1) -> 0 | J19: =COUNTIFS('F1 Foto (dati)'!$C$5:$C$84,A19,'F1 Foto (dati)'!$D$5:$D$84,B19,'F1 Foto (dati)'!$G$5:$G$84,"<>n.v.") -> 5 | K19: =IF(J19=0,0,I19/J19) -> 0 | L19: Nessuna squadra la riconosce come IA. PAS: "non ci aspettavamo che fosse vera"
A20: L4 | B20: 4 | C20: IA | D20: =INDEX('F1 Foto (dati)'!$F$5:$F$84,MATCH("TON|L4|4",'F1 Foto (dati)'!$A$5:$A$84,0)) -> IA | E20: =INDEX('F1 Foto (dati)'!$F$5:$F$84,MATCH("DIV|L4|4",'F1 Foto (dati)'!$A$5:$A$84,0)) -> IA | F20: =INDEX('F1 Foto (dati)'!$F$5:$F$84,MATCH("BIS|L4|4",'F1 Foto (dati)'!$A$5:$A$84,0)) -> Reale | G20: =INDEX('F1 Foto (dati)'!$F$5:$F$84,MATCH("PAS|L4|4",'F1 Foto (dati)'!$A$5:$A$84,0)) -> IA | H20: =INDEX('F1 Foto (dati)'!$F$5:$F$84,MATCH("DRE|L4|4",'F1 Foto (dati)'!$A$5:$A$84,0)) -> Reale | I20: =COUNTIFS('F1 Foto (dati)'!$C$5:$C$84,A20,'F1 Foto (dati)'!$D$5:$D$84,B20,'F1 Foto (dati)'!$G$5:$G$84,1) -> 3 | J20: =COUNTIFS('F1 Foto (dati)'!$C$5:$C$84,A20,'F1 Foto (dati)'!$D$5:$D$84,B20,'F1 Foto (dati)'!$G$5:$G$84,"<>n.v.") -> 5 | K20: =IF(J20=0,0,I20/J20) -> 0.6 | L20: Chi la riconosce lo fa dalle persone sullo sfondo
A22: Commenti scritti dalle squadre
A23: Tontony | B23: "Ci siamo accorti che alle volte è molto facile cadere nelle trappole dell'IA"
A24: Divo | B24: "Le iniziali erano molto semplici mentre il livello 4 era difficilissimo"
A25: Dream Team | B25: "È stato sconvolgente scoprire di non essere capaci di individuare nei livelli più avanzati le immagini create dall'IA"

Sheet F1bis Coppie
A1: Fase 1bis - Confronti: quale foto è stata generata dall'altra, e quella rimasta com'è?
A2: Soluzioni dalla presentazione: A = Foto 2 generata, Foto 1 a sua volta modificata; B = Foto 2 generata, Foto 1 autentica; C = Foto 1 generata, Foto 2 modificata
A4: Squadra | B4: Coppia | C4: Sol. foto generata | D4: Risposta | E4: Esito | F4: Sol. foto rimasta | G4: Risposta | H4: Esito | I4: Difficoltà | J4: Note / indizi
A5: Tontony | B5: A | C5: Foto 2 | D5: Foto 2 | E5: =IF(D5="","n.c.",IF(D5=C5,1,0)) -> 1 | F5: Modificata | G5: Modificata | H5: =IF(G5="","n.c.",IF(G5="?","n.v.",IF(G5=F5,1,0))) -> 1 | I5: 2 | J5: Componenti dell'auto sproporzionati
A6: Tontony | B6: B | C6: Foto 2 | D6: Foto 2 | E6: =IF(D6="","n.c.",IF(D6=C6,1,0)) -> 1 | F6: Autentica | G6: Autentica | H6: =IF(G6="","n.c.",IF(G6="?","n.v.",IF(G6=F6,1,0))) -> 1 | J6: Rossore sotto (gli occhi)
A7: Tontony | B7: C | C7: Foto 1 | D7: Foto 1 | E7: =IF(D7="","n.c.",IF(D7=C7,1,0)) -> 1 | F7: Modificata | G7: Modificata | H7: =IF(G7="","n.c.",IF(G7="?","n.v.",IF(G7=F7,1,0))) -> 1
A8: Divo | B8: A | C8: Foto 2 | D8: Foto 2 | E8: =IF(D8="","n.c.",IF(D8=C8,1,0)) -> 1 | F8: Modificata | G8: Autentica | H8: =IF(G8="","n.c.",IF(G8="?","n.v.",IF(G8=F8,1,0))) -> 0 | I8: 4 | J8: "ops"
A9: Divo | B9: B | C9: Foto 2 | D9: Foto 2 | E9: =IF(D9="","n.c.",IF(D9=C9,1,0)) -> 1 | F9: Autentica | G9: Autentica | H9: =IF(G9="","n.c.",IF(G9="?","n.v.",IF(G9=F9,1,0))) -> 1
A10: Divo | B10: C | C10: Foto 1 | E10: =IF(D10="","n.c.",IF(D10=C10,1,0)) -> n.c. | F10: Modificata | G10: Modificata | H10: =IF(G10="","n.c.",IF(G10="?","n.v.",IF(G10=F10,1,0))) -> 1 | J10: Foto generata non indicata
A11: Biscotto | B11: A | C11: Foto 2 | D11: Foto 2 | E11: =IF(D11="","n.c.",IF(D11=C11,1,0)) -> 1 | F11: Modificata | G11: Modificata | H11: =IF(G11="","n.c.",IF(G11="?","n.v.",IF(G11=F11,1,0))) -> 1
A12: Biscotto | B12: B | C12: Foto 2 | D12: Foto 2 | E12: =IF(D12="","n.c.",IF(D12=C12,1,0)) -> 1 | F12: Autentica | G12: Modificata | H12: =IF(G12="","n.c.",IF(G12="?","n.v.",IF(G12=F12,1,0))) -> 0
A13: Biscotto | B13: C | C13: Foto 1 | E13: =IF(D13="","n.c.",IF(D13=C13,1,0)) -> n.c. | F13: Modificata | H13: =IF(G13="","n.c.",IF(G13="?","n.v.",IF(G13=F13,1,0))) -> n.c. | J13: Non compilata
A14: Team Pasqua | B14: A | C14: Foto 2 | D14: Foto 2 | E14: =IF(D14="","n.c.",IF(D14=C14,1,0)) -> 1 | F14: Modificata | G14: Modificata | H14: =IF(G14="","n.c.",IF(G14="?","n.v.",IF(G14=F14,1,0))) -> 1 | J14: Troppo perfetta
A15: Team Pasqua | B15: B | C15: Foto 2 | D15: Foto 2 | E15: =IF(D15="","n.c.",IF(D15=C15,1,0)) -> 1 | F15: Autentica | G15: ? | H15: =IF(G15="","n.c.",IF(G15="?","n.v.",IF(G15=F15,1,0))) -> n.v. | J15: Autentica e Modificata entrambe barrate
A16: Team Pasqua | B16: C | C16: Foto 1 | E16: =IF(D16="","n.c.",IF(D16=C16,1,0)) -> n.c. | F16: Modificata | H16: =IF(G16="","n.c.",IF(G16="?","n.v.",IF(G16=F16,1,0))) -> n.c. | J16: Non compilata
A17: Dream Team | B17: A | C17: Foto 2 | D17: Foto 2 | E17: =IF(D17="","n.c.",IF(D17=C17,1,0)) -> 1 | F17: Modificata | G17: Autentica | H17: =IF(G17="","n.c.",IF(G17="?","n.v.",IF(G17=F17,1,0))) -> 0 | I17: 2
A18: Dream Team | B18: B | C18: Foto 2 | D18: Foto 2 | E18: =IF(D18="","n.c.",IF(D18=C18,1,0)) -> 1 | F18: Autentica | G18: Autentica | H18: =IF(G18="","n.c.",IF(G18="?","n.v.",IF(G18=F18,1,0))) -> 1 | I18: 4
A19: Dream Team | B19: C | C19: Foto 1 | D19: Foto 1 | E19: =IF(D19="","n.c.",IF(D19=C19,1,0)) -> 1 | F19: Modificata | G19: Modificata | H19: =IF(G19="","n.c.",IF(G19="?","n.v.",IF(G19=F19,1,0))) -> 1 | I19: 4
A21: Coppia | C21: Foto generata: corrette | D21: su compilate | F21: Foto rimasta: corrette | G21: su valide | J21: Lettura
A22: A | C22: =COUNTIFS($B$5:$B$19,A22,$E$5:$E$19,1) -> 5 | D22: =COUNTIFS($B$5:$B$19,A22,$E$5:$E$19,"<>n.c.") -> 5 | F22: =COUNTIFS($B$5:$B$19,A22,$H$5:$H$19,1) -> 3 | G22: =COUNTIFS($B$5:$B$19,A22,$H$5:$H$19,"<>n.c.",$H$5:$H$19,"<>n.v.") -> 5 | J22: Tutti trovano la foto generata, ma Divo e Dream Team credono autentica la foto di partenza, che era già stata modificata: nessuno si aspetta una doppia manipolazione.
A23: B | C23: =COUNTIFS($B$5:$B$19,A23,$E$5:$E$19,1) -> 5 | D23: =COUNTIFS($B$5:$B$19,A23,$E$5:$E$19,"<>n.c.") -> 5 | F23: =COUNTIFS($B$5:$B$19,A23,$H$5:$H$19,1) -> 3 | G23: =COUNTIFS($B$5:$B$19,A23,$H$5:$H$19,"<>n.c.",$H$5:$H$19,"<>n.v.") -> 4 | J23: Foto generata trovata da tutti; Biscotto pensa che anche l'originale sia modificata (eccesso di sospetto).
A24: C | C24: =COUNTIFS($B$5:$B$19,A24,$E$5:$E$19,1) -> 2 | D24: =COUNTIFS($B$5:$B$19,A24,$E$5:$E$19,"<>n.c.") -> 2 | F24: =COUNTIFS($B$5:$B$19,A24,$H$5:$H$19,1) -> 3 | G24: =COUNTIFS($B$5:$B$19,A24,$H$5:$H$19,"<>n.c.",$H$5:$H$19,"<>n.v.") -> 3 | J24: Biscotto e Team Pasqua non la compilano, Divo solo in parte; chi risponde lo fa correttamente.

Sheet Indizi usati
A1: Su cosa si basano per dire 'è fatta con l'IA'
A2: Ogni riga è un indizio scritto in una scheda. Esito = la risposta a cui l'indizio ha portato era giusta (1) o sbagliata (0)
A4: Categoria | B4: Squadra | C4: Riferimento | D4: Indizio scritto | E4: Risposta data | F4: Soluzione | G4: Esito
A5: Contesto implausibile | B5: Tontony | C5: F1-L0-F3 | D5: Non esiste tra le vesti papali | E5: IA | F5: IA | G5: =IF(E5="?","n.v.",IF(E5=F5,1,0)) -> 1
A6: Anatomia (mani, dita, collo) | B6: Tontony | C6: F1-L1-F1 | D6: Muscolatura del collo estrema: se allenasse il collo sarebbe anche più largo | E6: IA | F6: IA | G6: =IF(E6="?","n.v.",IF(E6=F6,1,0)) -> 1
A7: Sfondo e persone sullo sfondo | B7: Tontony | C7: F1-L2-F1 | D7: Differenziazioni nello sfondo secondario | E7: IA | F7: Reale | G7: =IF(E7="?","n.v.",IF(E7=F7,1,0)) -> 0
A8: Tratti del volto alterati | B8: Tontony | C8: F1-L2-F3 | D8: Tratti somatici modificati | E8: IA | F8: IA | G8: =IF(E8="?","n.v.",IF(E8=F8,1,0)) -> 1
A9: Filtri, colori, ritocco | B9: Tontony | C9: F1-L3-F3 | D9: Presenza di filtri | E9: IA | F9: IA | G9: =IF(E9="?","n.v.",IF(E9=F9,1,0)) -> 1
A10: Filtri, colori, ritocco | B10: Tontony | C10: F1-L4-F1 | D10: Contrasto elevato | E10: IA | F10: IA | G10: =IF(E10="?","n.v.",IF(E10=F10,1,0)) -> 1
A11: Filtri, colori, ritocco | B11: Tontony | C11: F1-L4-F2 | D11: Saturazione dei colori | E11: ? | F11: IA | G11: =IF(E11="?","n.v.",IF(E11=F11,1,0)) -> n.v.
A12: Sfondo e persone sullo sfondo | B12: Tontony | C12: F1-L4-F4 | D12: Persone sullo sfondo secondario irreali | E12: IA | F12: IA | G12: =IF(E12="?","n.v.",IF(E12=F12,1,0)) -> 1
A13: Pelle/volto 'troppo perfetti' | B13: Divo | C13: F1-L1-F1 | D13: Bambolina di porcellana | E13: IA | F13: IA | G13: =IF(E13="?","n.v.",IF(E13=F13,1,0)) -> 1
A14: Pelle/volto 'troppo perfetti' | B14: Divo | C14: F1-L2-F1 | D14: Pelle perfettissima, sfondo strano | E14: IA | F14: Reale | G14: =IF(E14="?","n.v.",IF(E14=F14,1,0)) -> 0
A15: Sfondo e persone sullo sfondo | B15: Divo | C15: F1-L2-F1 | D15: Pelle perfettissima, sfondo strano | E15: IA | F15: Reale | G15: =IF(E15="?","n.v.",IF(E15=F15,1,0)) -> 0
A16: Pelle/volto 'troppo perfetti' | B16: Divo | C16: F1-L2-F3 | D16: Troppo "perfetta" | E16: IA | F16: IA | G16: =IF(E16="?","n.v.",IF(E16=F16,1,0)) -> 1
... A46: Sfondo e persone sullo sfondo | B46: Dream Team | C46: F1-L4-F2 | D46: Sfondo | E46: IA | F46: IA | G46: =IF(E46="?","n.v.",IF(E46=F46,1,0)) -> 1
A47: Oggetti deformati o fusi | B47: Tontony | C47: F1bis-A | D47: Componenti dell'auto sproporzionati | E47: Foto 2 | F47: Foto 2 | G47: =IF(E47=F47,1,0) -> 1
A48: Tratti del volto alterati | B48: Tontony | C48: F1bis-B | D48: Rossore sotto (gli occhi) | E48: Foto 2 | F48: Foto 2 | G48: =IF(E48=F48,1,0) -> 1
A49: Pelle/volto 'troppo perfetti' | B49: Team Pasqua | C49: F1bis-A | D49: Troppo perfetta | E49: Foto 2 | F49: Foto 2 | G49: =IF(E49=F49,1,0) -> 1
A51: Riepilogo per categoria
A52: Categoria | B52: Citazioni | C52: Squadre che la usano | D52: Portano alla risposta giusta | E52: Affidabilità | H52: Lettura
A53: Pelle/volto 'troppo perfetti' | B53: =COUNTIF($A$5:$A$49,A53) -> 10 | C53: Biscotto, Divo, Dream Team, Team Pasqua | D53: =COUNTIFS($A$5:$A$49,A53,$G$5:$G$49,1) -> 9 | E53: =IFERROR(D53/COUNTIFS($A$5:$A$49,A53,$G$5:$G$49,"<>n.v."),0) -> 0.9 | H53: L'indizio più condiviso. Funziona sulle foto facili ma genera anche falsi allarmi su foto reali (F1-L2-F1).
A54: Sfondo e persone sullo sfondo | B54: =COUNTIF($A$5:$A$49,A54) -> 10 | C54: Biscotto, Divo, Dream Team, Team Pasqua, Tontony | D54: =COUNTIFS($A$5:$A$49,A54,$G$5:$G$49,1) -> 7 | E54: =IFERROR(D54/COUNTIFS($A$5:$A$49,A54,$G$5:$G$49,"<>n.v."),0) -> 0.7 | H54: Il più usato in assoluto e il più utile sui livelli difficili (persone sullo sfondo), ma uno 'sfondo dettagliato' viene letto anche come prova di realtà.
A55: Anatomia (mani, dita, collo) | B55: =COUNTIF($A$5:$A$49,A55) -> 4 | C55: Biscotto, Divo, Team Pasqua, Tontony | D55: =COUNTIFS($A$5:$A$49,A55,$G$5:$G$49,1) -> 3 | E55: =IFERROR(D55/COUNTIFS($A$5:$A$49,A55,$G$5:$G$49,"<>n.v."),0) -> 0.75 | H55: Utile (mignolo, collo) ma porta a errori quando un dettaglio reale sembra strano (la mano in F1-L2-F1).
A56: Luce, occhi, ombre | B56: =COUNTIF($A$5:$A$49,A56) -> 3 | C56: Divo, Team Pasqua | D56: =COUNTIFS($A$5:$A$49,A56,$G$5:$G$49,1) -> 3 | E56: =IFERROR(D56/COUNTIFS($A$5:$A$49,A56,$G$5:$G$49,"<>n.v."),0) -> 1 | H56: Usato poco, ma sempre con esito corretto.
A57: Filtri, colori, ritocco | B57: =COUNTIF($A$5:$A$49,A57) -> 7 | C57: Biscotto, Dream Team, Team Pasqua, Tontony | D57: =COUNTIFS($A$5:$A$49,A57,$G$5:$G$49,1) -> 3 | E57: =IFERROR(D57/COUNTIFS($A$5:$A$49,A57,$G$5:$G$49,"<>n.v."),0) -> 0.6 | H57: Confonde 'ritoccata' con 'generata': le foto reali con filtri vengono scambiate per IA.
A58: Oggetti deformati o fusi | B58: =COUNTIF($A$5:$A$49,A58) -> 4 | C58: Dream Team, Team Pasqua, Tontony | D58: =COUNTIFS($A$5:$A$49,A58,$G$5:$G$49,1) -> 4 | E58: =IFERROR(D58/COUNTIFS($A$5:$A$49,A58,$G$5:$G$49,"<>n.v."),0) -> 1 | H58: Indizio raro ma preciso (porta storta, auto sproporzionata).
A59: Contesto implausibile | B59: =COUNTIF($A$5:$A$49,A59) -> 3 | C59: Biscotto, Dream Team, Tontony | D59: =COUNTIFS($A$5:$A$49,A59,$G$5:$G$49,1) -> 3 | E59: =IFERROR(D59/COUNTIFS($A$5:$A$49,A59,$G$5:$G$49,"<>n.v."),0) -> 1 | H59: Funziona solo sul caso famoso (il Papa): utile per le foto virali, inutile sui selfie.
A60: Familiarità / somiglianza | B60: =COUNTIF($A$5:$A$49,A60) -> 2 | C60: Biscotto, Team Pasqua | D60: =COUNTIFS($A$5:$A$49,A60,$G$5:$G$49,1) -> 1 | E60: =IFERROR(D60/COUNTIFS($A$5:$A$49,A60,$G$5:$G$49,"<>n.v."),0) -> 0.5 | H60: Pericoloso: un volto che 'sembra conosciuto' rende la foto più credibile.
A61: Tratti del volto alterati | B61: =COUNTIF($A$5:$A$49,A61) -> 2 | C61: Tontony | D61: =COUNTIFS($A$5:$A$49,A61,$G$5:$G$49,1) -> 2 | E61: =IFERROR(D61/COUNTIFS($A$5:$A$49,A61,$G$5:$G$49,"<>n.v."),0) -> 1 | H61: Indizio fine, usato da una sola squadra.

Sheet F2 Chat
A1: Fase 2 - Fidarsi? Giudizio sulle chat
A2: Domanda 1 della scheda: 'Secondo voi è una chat sospetta di adescamento?' (le domande 2-3 sono state discusse a voce)
A4: Chat | B4: Tontony | C4: Divo | D4: Biscotto | E4: Team Pasqua | F4: Dream Team | G4: Sì | H4: No | I4: Non sappiamo | J4: Non compilata | K4: Consenso
A5: Chat 1 | B5: Sì | C5: No | D5: Sì | E5: Sì | F5: Sì | G5: =COUNTIF(B5:F5,"Sì") -> 4 | H5: =COUNTIF(B5:F5,"No") -> 1 | I5: =COUNTIF(B5:F5,"Non sappiamo") -> 0 | J5: =5-G5-H5-I5 -> 0 | K5: =IF(G5=5,"Unanime: sospetta",IF(G5>=(G5+H5+I5)*0.75,"Ampia maggioranza: sospetta",IF(G5>H5+I5,"Maggioranza: sospetta","Divisi / incerti"))) -> Ampia maggioranza: sospetta
A6: Chat 2 | B6: Non sappiamo | D6: Sì | F6: No | G6: =COUNTIF(B6:F6,"Sì") -> 1 | H6: =COUNTIF(B6:F6,"No") -> 1 | I6: =COUNTIF(B6:F6,"Non sappiamo") -> 1 | J6: =5-G6-H6-I6 -> 2 | K6: =IF(G6=5,"Unanime: sospetta",IF(G6>=(G6+H6+I6)*0.75,"Ampia maggioranza: sospetta",IF(G6>H6+I6,"Maggioranza: sospetta","Divisi / incerti"))) -> Divisi / incerti
A7: Chat 3 | B7: Sì | C7: Sì | D7: Sì | E7: Sì | F7: No | G7: =COUNTIF(B7:F7,"Sì") -> 4 | H7: =COUNTIF(B7:F7,"No") -> 1 | I7: =COUNTIF(B7:F7,"Non sappiamo") -> 0 | J7: =5-G7-H7-I7 -> 0 | K7: =IF(G7=5,"Unanime: sospetta",IF(G7>=(G7+H7+I7)*0.75,"Ampia maggioranza: sospetta",IF(G7>H7+I7,"Maggioranza: sospetta","Divisi / incerti"))) -> Ampia maggioranza: sospetta
A8: Chat 4 (parte 1 e 2) | B8: Sì | D8: Sì | E8: Sì | F8: Sì | G8: =COUNTIF(B8:F8,"Sì") -> 4 | H8: =COUNTIF(B8:F8,"No") -> 0 | I8: =COUNTIF(B8:F8,"Non sappiamo") -> 0 | J8: =5-G8-H8-I8 -> 1 | K8: =IF(G8=5,"Unanime: sospetta",IF(G8>=(G8+H8+I8)*0.75,"Ampia maggioranza: sospetta",IF(G8>H8+I8,"Maggioranza: sospetta","Divisi / incerti"))) -> Ampia maggioranza: sospetta
A9: Chat 5 | B9: Sì | C9: Sì | D9: Sì | E9: Sì | F9: Non sappiamo | G9: =COUNTIF(B9:F9,"Sì") -> 4 | H9: =COUNTIF(B9:F9,"No") -> 0 | I9: =COUNTIF(B9:F9,"Non sappiamo") -> 1 | J9: =5-G9-H9-I9 -> 0 | K9: =IF(G9=5,"Unanime: sospetta",IF(G9>=(G9+H9+I9)*0.75,"Ampia maggioranza: sospetta",IF(G9>H9+I9,"Maggioranza: sospetta","Divisi / incerti"))) -> Ampia maggioranza: sospetta
A11: Cosa hanno notato, chat per chat
A12: Chat | B12: Note scritte dai gruppi | F12: Osservazioni del team (codici OSS) | K12: Punti comuni / divergenze
A13: Chat 1 | B13: [CH-TON-C1] Tontony: Vittimismo finale, trucco psicologico; non rivela l'identità e fa domande sospette; risponde troppo velocemente [CH-DRE-C1] Dream Team: Domande strane, un po' da stalker; chiede foto; evita i problemi | F13: [OSS-01] Chat percepita come normale, forse "pressa un po' troppo" [OSS-02] Notano la schermata centrale: controllare il telefono e inventare scuse [OSS-03] Lo bloccherebbero [OSS-04] L'ultima schermata, gli ultimi messaggi sono i peggiori (escalation) [OSS-05] Molti capiscono che la chat 1 è pericolosa e discutono sia dei messaggi sia delle risposte | K13: COMUNE: riconoscono l'escalation finale e la richiesta di nascondere/controllare il telefono; reazione tipica: bloccare. DIVERGENZA: Divo la giudica non sospetta e un'osservazione la descrive come 'chat normale': i segnali iniziali sono deboli e vengono notati solo alla fine.
A14: Chat 2 | B14: [CH-DRE-C2] Dream Team: Manda foto fatte con l'IA; chiede foto | F14: - | K14: DIVERGENZA FORTE: Biscotto Sì, Dream Team No (pur annotando foto fatte con l'IA e richiesta di foto), Tontony 'non sappiamo', 2 squadre non rispondono. Chat su cui manca un criterio condiviso.
A15: Chat 3 | B15: [CH-TON-C3] Tontony: Ha degli elementi genuini e anche un po' tossici. Il cercare il confronto frontale fa pensare a un sì però [CH-DIV-C3] Divo: "Sembra un account" (profilo costruito/falso) | F15: [OSS-07] Si fanno troppa confidenza senza conoscersi ("non ti tratterei mai così"); insistenza nella richiesta della foto [OSS-08] Notano la foto finta inviata nella chat e quindi i metodi per guadagnare fiducia [OSS-09] Notano gli orari dei messaggi come possibile indicatore di sospetto | K15: COMUNE: troppa confidenza senza conoscersi, insistenza sulla foto, foto finta usata per guadagnare fiducia, orari sospetti. DIVERGENZA: Tontony vede 'elementi genuini' (la proposta di vedersi di persona sembra una garanzia); Dream Team la giudica non sospetta.
A16: Chat 4 (parte 1 e 2) | B16: [CH-TON-C4] Tontony: Spostarsi su Snapchat; frase di lusinga esagerata ("unica...", lettura incerta); poi chiede di non presentarsi con altri [CH-DRE-C4] Dream Team: Un po' pervertito; cerca di isolarti ("cerca la solitudine"); una foto finta; chiede dati personali; stalker; passaggio di app sospetto | F16: [OSS-10] Pressa troppo soprattutto nella fase finale ("Alle 4 in Duomo..."), però "se lo conosco da un po' ci può stare" [OSS-11] Mancano riferimenti: nessuno chiede ulteriori prove a lui, accettano passivamente il suo comportamento [OSS-12] Stalker: sa cose che non sono state dette; scrive nonostante la differenza di età [OSS-13] Passaggio a Snapchat; tono aggressivo; chiede di venire da sola e di mentire ai genitori [OSS-14] Chiede dati personali e dettagli che i ragazzi non se la sentono di condividere; mettono in discussione il passaggio a Snapchat [OSS-15] Se non lo conoscono non danno il numero o altri dettagli, per non essere tracciati/seguiti su altre piattaforme [OSS-16] Per le ragazze è strano che un ragazzo di 21 anni scriva a una ragazza di 16: chat sospetta [OSS-17] La foto sembra falsa, quindi non si fiderebbero a continuare la conversazione | K16: COMUNE: la chat più riconosciuta: cambio di app (Snapchat), richiesta di venire da sola e mentire ai genitori, differenza d'età, dati personali, sa cose non dette. SORPRESA: 'se lo conosco da un po' ci può stare' e nessuno chiede prove della sua identità (OSS-10, OSS-11).
A17: Chat 5 | B17: [CH-TON-C5] Tontony: Contraddizione nel "dove ti ho visto". Dopo aver condiviso la foto, l'adescatore non risponde più [CH-DRE-C5] Dream Team: Stalker, pervertito | F17: [OSS-18] I genitori vengono "saltati": vanno alla polizia postale o avvisano loro gli amici che le foto sono fake, mai dai genitori (poca confidenza o timore) [OSS-19] Interlocutore vago, omette informazioni, insistente, fa molte domande [OSS-20] La vittima non vuole dirlo a nessuno (comprensibile) ma bisogna parlarne: prima con persone di confidenza (sorella, amica), poi con i genitori, per sentire più pareri [OSS-21] Alcuni andrebbero avanti per capire di più su Luca; altri notano la contraddizione (dice di aver visto Matteo alla partita ma gli chiede una foto con la maglia) [OSS-22] Non avrebbero inviato la foto; in caso di sospetto lo direbbero ai genitori | K17: COMUNE: nessuno manderebbe la foto; notano la contraddizione 'ti ho visto alla partita'. DIVERGENZA: a chi chiederebbero aiuto: polizia postale e amici saltando i genitori (OSS-18), prima sorella/amica e poi genitori (OSS-20), direttamente i genitori (OSS-22). Alcuni andrebbero avanti per curiosità (OSS-21).
A18: Chat 5.1 | B18: [CH-DRE-C5.1] Dream Team: Cyberbullismo modificando foto | F18: [OSS-23] La foto modificata inoltrata nel gruppo è vista come uno scherzo; se girasse in più gruppi o con sconosciuti la prenderebbero più seriamente. Sensibilità parziale: va chiarito quando diventa grave [OSS-24] Non si mandano foto modificate con l'IA sul gruppo, la prenderebbero male indipendentemente dal tono; dipende dal soggetto preso di mira, ma se la prende male è giusto eliminarla [OSS-25] Considerano la chat uno scherzo nonostante Matteo sia uscito dal gruppo e abbia chiesto di togliere la foto | K18: DIVERGENZA: per alcuni la foto modificata nel gruppo è uno scherzo anche quando la vittima esce dal gruppo (OSS-25); per altri non si fa mai (OSS-24). Biscotto la prenderebbe sul serio solo se girasse fuori dal gruppo (OSS-23).
A19: Chat 6 | B19: [CH-DRE-C6] Dream Team: Parlare con un adulto o con qualcuno che ti possa aiutare | F19: - | K19: Nessuna squadra ha segnato la risposta preferita di Giulia. Dream Team scrive che bisogna parlare con un adulto o con qualcuno che può aiutare.

Sheet Tavola rotonda
A1: Tavola rotonda - risposte alle domande TR1-TR4
A4: Domanda | B4: Sotto-domanda (co-design) | C4: Tontony | D4: Divo | E4: Biscotto | F4: Team Pasqua | G4: Dream Team | H4: Punti comuni | I4: Divergenze | J4: Bisogni
A5: TR1. Quando vi scrive qualcuno che non conoscete, su cosa vi basate per decidere se fidarvi? | B5: Vi piacerebbe che un servizio vi insegnasse come riconoscere i segnali più affidabili da chi vi scrive? In che forma? (consigli brevi, esempi, video, giochi interattivi, botta e risposta) | C5: Questo progetto ci ha interessato perché ci ha fatto agire in prima persona, con giochi e quiz interattivi. Ci piacerebbe la presenza di un servizio educativo al comportamento online. | D5: Rispondo ma faccio sia domande sia risposte "basilari", cose di poco conto. Se ci rendiamo conto che c'è un pericolo smettiamo. Guardiamo anche gli amici in comune e le storie in evidenza (se ci sono). Sì, ci piacerebbe, magari attraverso ore scolastiche più interattive come oggi o cose più tecnologiche, non una lezione come le solite. | E5: In base ai messaggi che manda e al fatto se è insistente o meno. Incontri come oggi possono servire e sono belli. | F5: Mi fido di più se ci sono degli amici in comune e se l'ho visto almeno una volta in giro o a scuola. Inoltre ci piacerebbe avere un servizio per essere più consapevoli. | G5: Se lo conosco già dal vivo mi fido, altrimenti no. | H5: Ci si fida di chi si conosce dal vivo o di chi ha amici in comune / storie in evidenza; insistenza come campanello. Tutte le squadre che rispondono alla sotto-domanda vogliono un servizio educativo, purché attivo e interattivo ('come oggi', giochi e quiz). | I5: Strategie diverse: Dream Team non si fida mai di chi non conosce dal vivo; Divo risponde 'con cose basilari' e smette solo se avverte il pericolo (mette alla prova la conversazione invece di chiudere). | J5: B1, B3, B6
A6: TR2. Vi sentite capaci di riconoscere una foto fatta con l'IA? Cosa vi rende sicuri? | B6: Preferite ricevere feedback dalla piattaforma o vi stimola di più un gioco tipo vero o falso, con punti, livelli e sfide anche con amici online? | C6: Ci sentiamo abbastanza sicuri, anche se davanti al livello difficile del quiz ci siamo resi conto di quanto può essere facile essere adescati online. | D6: Abbastanza, soprattutto rispetto a certi adulti. Siamo più abituati a stare in contatto con l'IA. | E6: Sì, nella maggior parte dei casi, ma alcune ingannano. Guardare i dettagli. | F6: Riconosciamo la maggior parte delle foto fatte con l'IA, eccetto alcune. | G6: No, [la percezione sui volti è difficile - lettura incerta]. Gioco con punti e livelli online con gli amici. | H6: Si sentono 'abbastanza' capaci, ma ammettono che alcune foto ingannano; la sicurezza viene dal 'guardare i dettagli'. | I6: Divo si sente più capace degli adulti 'perché più abituati all'IA'; Dream Team risponde 'No' e indica il gioco a punti e livelli con amici; Tontony dice che il livello difficile ha fatto capire quanto è facile cadere. | J6: B4, B1
A7: TR3. Siete d'accordo nell'avere un forum come spazio condiviso? | B7: Deve esserci solo pubblicazione e lettura delle esperienze, o anche reazioni e commenti (revisionati per evitare commenti inappropriati)? | C7: Sì, siamo d'accordo perché l'esperienza del singolo può aiutare il gruppo, ma altre persone possono screditare queste esperienze utili. | D7: Sì, sarebbe un'ottima opzione; dovrebbero esserci più possibilità sociali (reazioni/commenti). | E7: Se ci sono consigli ed esperienze sì, ma non condivideremmo esperienze personali. | F7: Noi manterremmo le interazioni e i commenti, soprattutto se le piattaforme online incrementassero la sicurezza e controllassero i commenti negativi. | G7: Non saprei come risponderei, dato che non ho mai fatto un'esperienza in un forum. | H7: Il forum piace come luogo per leggere esperienze e consigli. | I7: Sulla scrittura: Biscotto non condividerebbe esperienze personali; Team Pasqua e Divo vogliono commenti e reazioni ma moderati; Tontony teme che altri 'screditino' le esperienze; Dream Team non ha mai usato un forum. | J7: B2
A8: TR4. Quali sono i principali motivi per cui diffidate nel parlarne con gli adulti? | B8: È utile inserire nell'app la possibilità di fare da tutor su questa problematica? Può aumentare la probabilità di parlarne o resta la paura? | C8: A quest'età si tende ad apprendere il mondo a modo proprio, senza chiedere consiglio a nessuno. Questa pratica può avere un risvolto negativo quando si nascondono fatti gravi. | D8: Perché spesso reagiscono senza cercare un punto d'incontro o di capire cosa proviamo e in che società ormai viviamo. Il tutor sarebbe utilissimo. | E8: Dover affrontare le conseguenze, essere giudicata e non avere più la libertà di prima. | F8: Ci affidiamo agli adulti perché riconosciamo in loro maggiore stabilità e maturità. Non siamo d'accordo sul tutor online perché è meglio confidarsi con qualcuno che conosci, di cui ti fidi e che può darti consigli migliori conoscendo il tuo carattere. | G8: La convinzione di poter risolvere tutto da soli e il disagio, dato che è molto difficile una conversazione. Secondo noi [il tutor] può aiutare i genitori a intervenire in questo frangente [lettura incerta]. | H8: Tutte le squadre descrivono una difficoltà a parlarne con gli adulti: paura delle conseguenze, del giudizio, di perdere libertà; adulti che reagiscono senza capire; la convinzione di farcela da soli. | I8: Sul tutor: Divo lo trova utilissimo; Team Pasqua contraria (meglio qualcuno che ti conosce) e, unica, dice di affidarsi agli adulti; Dream Team lo vede come ponte verso i genitori. | J8: B7, B5

Sheet Appunti osservazione
A1: Appunti di osservazione del team, codificati
A4: Codice | B4: Chat / momento | C4: Squadra (se nota) | D4: Appunto | E4: Tema
A5: OSS-01 | B5: Chat 1 | D5: Chat percepita come normale, forse "pressa un po' troppo" | E5: Riconoscimento segnali
A6: OSS-02 | B6: Chat 1 | D6: Notano la schermata centrale: controllare il telefono e inventare scuse | E6: Riconoscimento segnali
A7: OSS-03 | B7: Chat 1 | D7: Lo bloccherebbero | E7: Reazione
A8: OSS-04 | B8: Chat 1 | D8: L'ultima schermata, gli ultimi messaggi sono i peggiori (escalation) | E8: Riconoscimento segnali
A9: OSS-05 | B9: Chat 1 | D9: Molti capiscono che la chat 1 è pericolosa e discutono sia dei messaggi sia delle risposte | E9: Riconoscimento segnali
A10: OSS-06 | B10: Generale | D10: Molti sono diffidenti verso sconosciuti che fanno richieste esplicite, altri accettano richieste da sconosciuti | E10: Criteri di fiducia
A11: OSS-07 | B11: Chat 3 | D11: Si fanno troppa confidenza senza conoscersi ("non ti tratterei mai così"); insistenza nella richiesta della foto | E11: Riconoscimento segnali
A12: OSS-08 | B12: Chat 3 | D12: Notano la foto finta inviata nella chat e quindi i metodi per guadagnare fiducia | E12: Deepfake nelle chat
A13: OSS-09 | B13: Chat 3 | D13: Notano gli orari dei messaggi come possibile indicatore di sospetto | E13: Riconoscimento segnali
A14: OSS-10 | B14: Chat 4.1-4.2 | D14: Pressa troppo soprattutto nella fase finale ("Alle 4 in Duomo..."), però "se lo conosco da un po' ci può stare" | E14: Criteri di fiducia
A15: OSS-11 | B15: Chat 4.1-4.2 | D15: Mancano riferimenti: nessuno chiede ulteriori prove a lui, accettano passivamente il suo comportamento | E15: Verifica identità
A16: OSS-12 | B16: Chat 4.1 | D16: Stalker: sa cose che non sono state dette; scrive nonostante la differenza di età | E16: Riconoscimento segnali
... A18: OSS-14 | B18: Chat 4 | D18: Chiede dati personali e dettagli che i ragazzi non se la sentono di condividere; mettono in discussione il passaggio a Snapchat | E18: Riconoscimento segnali
A19: OSS-15 | B19: Chat 4 | C19: BIS o PAS | D19: Se non lo conoscono non danno il numero o altri dettagli, per non essere tracciati/seguiti su altre piattaforme | E19: Protezione dati
A20: OSS-16 | B20: Chat 4.1-4.2 | D20: Per le ragazze è strano che un ragazzo di 21 anni scriva a una ragazza di 16: chat sospetta | E20: Riconoscimento segnali
A21: OSS-17 | B21: Chat 4.1-4.2 | D21: La foto sembra falsa, quindi non si fiderebbero a continuare la conversazione | E21: Deepfake nelle chat
A22: OSS-18 | B22: Chat 5 | D22: I genitori vengono "saltati": vanno alla polizia postale o avvisano loro gli amici che le foto sono fake, mai dai genitori (poca confidenza o timore) | E22: Rapporto con gli adulti
A23: OSS-19 | B23: Chat 5 | D23: Interlocutore vago, omette informazioni, insistente, fa molte domande | E23: Riconoscimento segnali
A24: OSS-20 | B24: Chat 5 | D24: La vittima non vuole dirlo a nessuno (comprensibile) ma bisogna parlarne: prima con persone di confidenza (sorella, amica), poi con i genitori, per sentire più pareri | E24: Rapporto con gli adulti
A25: OSS-21 | B25: Chat 5 | D25: Alcuni andrebbero avanti per capire di più su Luca; altri notano la contraddizione (dice di aver visto Matteo alla partita ma gli chiede una foto con la maglia) | E25: Riconoscimento segnali
A26: OSS-22 | B26: Chat 5 | D26: Non avrebbero inviato la foto; in caso di sospetto lo direbbero ai genitori | E26: Rapporto con gli adulti
A27: OSS-23 | B27: Chat 5.1 | C27: BIS | D27: La foto modificata inoltrata nel gruppo è vista come uno scherzo; se girasse in più gruppi o con sconosciuti la prenderebbero più seriamente. Sensibilità parziale: va chiarito quando diventa grave | E27: Gravità contenuti manipolati
A28: OSS-24 | B28: Chat 5.1 | D28: Non si mandano foto modificate con l'IA sul gruppo, la prenderebbero male indipendentemente dal tono; dipende dal soggetto preso di mira, ma se la prende male è giusto eliminarla | E28: Gravità contenuti manipolati
A29: OSS-25 | B29: Chat 5.1 | D29: Considerano la chat uno scherzo nonostante Matteo sia uscito dal gruppo e abbia chiesto di togliere la foto | E29: Gravità contenuti manipolati
A30: OSS-26 | B30: Domanda 3 | D30: Il forum è interessante per vedere cosa è successo ad altri e sentirsi meno soli, ma non spinge le ragazze a scrivere le loro esperienze (molto titubanti) | E30: Confronto tra pari
A31: OSS-27 | B31: Generale | D31: Alcuni studenti non prendono seriamente l'attività | E31: Coinvolgimento
A32: OSS-28 | B32: Generale | D32: Difficoltà iniziali a capire l'attività, poi "a gonfie vele" | E32: Coinvolgimento
B34: Tema | C34: N. appunti
B35: Coinvolgimento | C35: =COUNTIF($E$5:$E$32,B35) -> 2
B36: Confronto tra pari | C36: =COUNTIF($E$5:$E$32,B36) -> 1
B37: Criteri di fiducia | C37: =COUNTIF($E$5:$E$32,B37) -> 2
B38: Deepfake nelle chat | C38: =COUNTIF($E$5:$E$32,B38) -> 2
B39: Gravità contenuti manipolati | C39: =COUNTIF($E$5:$E$32,B39) -> 3
B40: Protezione dati | C40: =COUNTIF($E$5:$E$32,B40) -> 1
B41: Rapporto con gli adulti | C41: =COUNTIF($E$5:$E$32,B41) -> 3
B42: Reazione | C42: =COUNTIF($E$5:$E$32,B42) -> 1
B43: Riconoscimento segnali | C43: =COUNTIF($E$5:$E$32,B43) -> 12
B44: Verifica identità | C44: =COUNTIF($E$5:$E$32,B44) -> 1

Sheet Analisi tematica
A1: Analisi tematica - dai dati ai bisogni
A2: Per ogni tema: cosa dicono le fonti, dove i gruppi concordano o divergono, e quale bisogno ne deriva
A4: Tema | B4: Cosa emerge | C4: Evidenze (codici) | D4: Convergenza | E4: Divergenza | F4: Insight per il progetto | G4: Bisogno
A5: T1. Sovrastima delle proprie capacità | B5: Autovalutazione media 6,6/10 sulle foto e 7/10 sulle chat. Accuratezza 93% ai livelli 0-1, 53% al livello 4; una foto IA del livello 4 non viene riconosciuta da nessuno. La fiducia non cambia con la difficoltà: chi si dichiara più prudente (Team Pasqua) va meglio sui contenuti difficili. | C5: F0; F1-L4-F3; F1bis-A; TR2-TON, TR2-DIV, TR2-DRE; commenti TON, DIV, DRE | D5: Tutte le squadre sbagliano almeno una foto del livello 4 e 3 squadre scrivono spontaneamente di essere rimaste sorprese. | E5: Divo si dichiara più capace degli adulti; Dream Team dice esplicitamente 'No'. | F5: Il momento di 'scoperta' dell'errore è stato il più potente dell'attività: il prodotto deve farlo vivere, non solo raccontarlo. | G5: B4
A6: T2. Indizi visivi poco affidabili | B6: Gli indizi più usati ('troppo perfetto', sfondo, ritocco) funzionano sulle foto facili ma producono falsi allarmi su foto reali e falsa sicurezza su foto IA ben fatte; la familiarità di un volto aumenta la fiducia. | C6: Foglio 'Indizi usati'; F1-L2-F1; F1-L1-F3; F1-L3-F3 (BIS) | D6: Tutti cercano dettagli anomali nell'immagine. | E6: C'è chi confonde 'ritoccata' e 'generata'. | F6: Insegnare 'come guardare' non basta: serve spostare l'attenzione dall'immagine al contesto (chi la manda, perché, cosa chiede). | G6: B4, B6
A7: T3. Criteri di fiducia fragili | B7: Ci si fida per amici in comune, storie in evidenza, averlo visto a scuola, 'lo conosco da un po''. Nessuno chiede prove dell'identità; la proposta di incontrarsi viene letta come garanzia. | C7: TR1-DIV, TR1-PAS, TR1-DRE; OSS-10, OSS-11; CH-TON-C3 | D7: Tutti hanno un criterio di fiducia, quasi sempre basato su segnali sociali. | E7: Dream Team: fiducia solo a chi si conosce dal vivo. | F7: I segnali sociali sono esattamente ciò che un adescatore (aiutato dall'IA) può costruire: va reso esplicito e allenato il 'verificare'. | G7: B6
A8: T4. Riconoscimento dei segnali nelle chat | B8: Le richieste esplicite (foto, dati, cambio app, venire da sola, mentire ai genitori) vengono riconosciute bene; i segnali graduali e la manipolazione emotiva ('non ti tratterei mai così', vittimismo) vengono notati tardi. | C8: F2 (consenso); OSS-01, OSS-04, OSS-05, OSS-07, OSS-12, OSS-13, OSS-16; CH-TON-C1, CH-DRE-C4 | D8: Chat 4 e 5 giudicate sospette quasi da tutti; individuano bene l'escalation finale. | E8: Chat 1, 2, 3: almeno una squadra le considera non sospette o non sa. | F8: Il pericolo si riconosce alla fine della conversazione, quando è già avanzata: serve allenare il riconoscimento precoce. | G8: B3
A9: T5. Barriera verso gli adulti | B9: Paura delle conseguenze, del giudizio, di perdere libertà; adulti che reagiscono senza capire; volersela cavare da soli. Si passa da amici, sorelle o direttamente dalla polizia postale. | C9: TR4 (tutte le squadre); OSS-18, OSS-20, OSS-22 | D9: Tutte le squadre parlano della difficoltà a dirlo ai genitori. | E9: Team Pasqua si affida agli adulti; un gruppo lo direbbe ai genitori in caso di sospetto (OSS-22). | F9: Il problema non è sapere che bisogna parlarne, ma riuscire a farlo: serve un passo intermedio che abbassi il costo emotivo. | G9: B7, B5
A10: T6. Confronto tra pari e anonimato | B10: Il forum interessa per sentirsi meno soli e imparare dagli altri, ma pochi scriverebbero la propria esperienza; chi accetta i commenti chiede moderazione. | C10: TR3 (tutte); OSS-26 | D10: Lettura di esperienze altrui: sì per quasi tutti. | E10: Scrivere/commentare: da 'non condivideremmo' (BIS) a 'manterremmo commenti se moderati' (PAS, DIV). | F10: Il valore è soprattutto nel leggere: la partecipazione attiva va resa facoltativa e protetta. | G10: B2
A11: T7. Deepfake 'per scherzo' tra pari | B11: La foto modificata con l'IA e girata nel gruppo viene spesso letta come scherzo, anche quando la vittima chiede di toglierla; la gravità viene legata alla diffusione (più gruppi, sconosciuti) e non al danno per la persona. | C11: OSS-23, OSS-24, OSS-25; CH-DRE-C5.1 | D11: C'è una sensibilità di base: tutti riconoscono che 'dipende' e che a un certo punto diventa grave. | E11: Da 'non si fa mai' a 'è uno scherzo'. | F11: Manca un criterio condiviso per capire quando lo scherzo diventa violenza e cosa può fare chi assiste. | G11: B8
A12: T8. Modalità di apprendimento | B12: L'attività è piaciuta perché attiva (quiz a livelli, chat da analizzare); chiedono ore più interattive e non 'la solita lezione'; un gruppo cita punti, livelli e sfide con gli amici. | C12: TR1-TON, TR1-DIV, TR1-BIS; TR2-DRE; OSS-27, OSS-28 | D12: Apprezzamento del formato da tutte le squadre che lo commentano. | E12: Alcuni studenti non hanno preso sul serio l'attività: il gioco coinvolge ma rischia di banalizzare. | F12: L'elemento di gioco è un requisito sulla modalità (come) più che un bisogno (cosa): va bilanciato con la serietà del tema. | G12: B1
A14: Bisogni consolidati (dettaglio nel documento Word)
A15: Codice | B15: Bisogno | C15: Origine | D15: Stato | E15: In breve
A16: B1 | B16: Imparare in modo attivo e coinvolgente, non con la solita lezione | C16: Bisogno 1 (Gamification) | D16: Confermato, riformulato | E16: Imparare facendo (sfide, quiz, livelli) invece che ascoltando
A17: B2 | B17: Imparare dalle esperienze dei coetanei sentendosi protetti e meno soli | C17: Bisogno 2 (Confronto con coetanei e testimonianze anonime) | D17: Confermato e ampliato | E17: Leggere esperienze reali di pari, con anonimato e moderazione
A18: B3 | B18: Riconoscere i segnali dell'adescamento, anche quando arrivano poco alla volta | C18: Bisogno 3 (Conoscenza dei temi e consapevolezza dei rischi) | D18: Confermato e ampliato | E18: Conoscere tecniche e segnali (insistenza, isolamento, cambio app, escalation)
A19: B4 | B19: Avere un'idea realistica di quanto si è capaci di riconoscere un falso | C19: Bisogno 4 (Più consapevolezza delle proprie capacità) | D19: Confermato | E19: Calibrare la fiducia in sé: i ragazzi si sopravvalutano sui contenuti difficili
A20: B5 | B20: Sapere cosa fare e a chi rivolgersi quando qualcosa non va | C20: Bisogno 5 (Aiuto al supporto e contatti) | D20: Confermato e precisato | E20: Passi concreti e canali (amici, adulti, polizia postale) al momento giusto
A21: B6 | B21: Verificare chi c'è davvero dall'altra parte con criteri affidabili | C21: Nuovo (emerso da Fase 2 e appunti) | D21: Nuovo | E21: I criteri usati (amici in comune, storie, 'lo conosco da un po'') sono facili da falsificare
A22: B7 | B22: Poter coinvolgere un adulto di fiducia senza paura di giudizio o di perdere libertà | C22: Nuovo (emerso da TR4 e Chat 5) | D22: Nuovo | E22: La barriera verso i genitori è il motivo principale per cui si tace
A23: B8 | B23: Capire quando un contenuto manipolato con l'IA smette di essere uno scherzo | C23: Nuovo (emerso da Chat 5.1) | D23: Nuovo | E23: Il deepfake 'per ridere' nel gruppo non viene percepito come violenza
